{"_ts": 1772599643.6266925, "data": {"metadata": {"dataVersion": "2", "matchId": "BR1_3213632942", "participants": ["pWv9nxzEQ9DqiPT8uuDi2MVKv4Gy01qmQceCfzNNsT9dtugE3rhQMLImjZoicriOGRCXaORzpInwjg", "XuksM654VP2A149mMwfsuNn6k3L13SS5ziBllb8IOLIMjD4PpHMmQaf8cIIVLlLEH0-QrgFdxWGZAw", "XGmv-8vX9SJcwKVfpfWjcPFerisOXJ6WTx8t5rEK-QklpDM6WIoa2HMd2-GKKU6WY8VkF0m7oIe-kA", "wCOAXejv6qFJ8CfuqJO7LL5X56Dr4Bdb6MVNfDkj03HaZoIDGkSMxGRpZUC8uIN0UXSPMNAr1D30Nw", "wcWDFtQRdWqCboDhrPT_ZTTNEgWXSJ8KNoakADocffHFS871blVGNcI2Gh7n7QU3kGZOIfuzCVFfgw", "XLNZ3OrbT5DcPp-IL98dkC_uT1fF8ihkGaZ0f9yUsQcFnV0UPzqtWef77c3MTRzQP7f3_LH_oLN0pw", "Dc1BTdABq49Dnd4NS5ZSFWwnauzzLyXRTyPdyPbDkhuuPGSPAykkPVHnib-eF0UviZn9DeoLN2VBIw", "Pr48DetWYymD2yHSbCibB5rTHlBhLdCMORXDyLm521PAGIU2AZ8d9TqZmqi3T6QmIq1-u5kV0fDRSw", "vcwAvwlpCKr-UXe349t9Ksw1oJw7m1kQQBev4yCBZfRYi4qYV5KZSvJmBh3L_T5KOcslUfrceaI-kw", "h5JfrQxLv_LGxDUMrdE8z0ayb_aBM-cICTz1OXfmLRzfzhg8aezQzYuU_01rjEyHh_TrzKwubbW6nQ"]}, "info": {"endOfGameResult": "GameComplete", "gameCreation": 1772598368143, "gameDuration": 921, "gameEndTimestamp": 1772599347251, "gameId": 3213632942, "gameMode": "CLASSIC", "gameName": "teambuilder-match-3213632942", "gameStartTimestamp": 1772598426172, "gameType": "MATCHED_GAME", "gameVersion": "16.4.748.682", "mapId": 11, "participants": [{"PlayerBehavior": {"PlayerBehavior_IsHeroInCombat": 0}, "PlayerScore0": 0, "PlayerScore1": 0, "PlayerScore10": 0, "PlayerScore11": 0, "PlayerScore2": 0, "PlayerScore3": 0, "PlayerScore4": 0, "PlayerScore5": 0, "PlayerScore6": 0, "PlayerScore7": 0, "PlayerScore8": 0, "PlayerScore9": 0, "allInPings": 0, "assistMePings": 1, "assists": 0, "baronKills": 0, "basicPings": 0, "challenges": {"12AssistStreakCount": 0, "HealFromMapSources": 253.7412452697754, "InfernalScalePickup": 0, "SWARM_DefeatAatrox": 0, "SWARM_DefeatBriar": 0, "SWARM_DefeatMiniBosses": 0, "SWARM_EvolveWeapon": 0, "SWARM_Have3Passives": 0, "SWARM_KillEnemy": 0, "SWARM_PickupGold": 0, "SWARM_ReachLevel50": 0, "SWARM_Survive15Min": 0, "SWARM_WinWith5EvolvedWeapons": 0, "abilityUses": 142, "acesBefore15Minutes": 0, "alliedJungleMonsterKills": 0, "baronTakedowns": 0, "blastConeOppositeOpponentCount": 0, "bountyGold": 0, "buffsStolen": 0, "completeSupportQuestInTime": 0, "controlWardsPlaced": 0, "damagePerMinute": 472.1796220978481, "damageTakenOnTeamPercentage": 0.2240251443845993, "dancedWithRiftHerald": 0, "deathsByEnemyChamps": 2, "dodgeSkillShotsSmallWindow": 0, "doubleAces": 0, "dragonTakedowns": 0, "earlyLaningPhaseGoldExpAdvantage": 0, "effectiveHealAndShielding": 0, "elderDragonKillsWithOpposingSoul": 0, "elderDragonMultikills": 0, "enemyChampionImmobilizations": 4, "enemyJungleMonsterKills": 0, "epicMonsterKillsNearEnemyJungler": 1, "epicMonsterKillsWithin30SecondsOfSpawn": 0, "epicMonsterSteals": 0, "epicMonsterStolenWithoutSmite": 0, "firstTurretKilled": 0, "fistBumpParticipation": 0, "flawlessAces": 0, "fullTeamTakedown": 0, "gameLength": 921.399431054, "getTakedownsInAllLanesEarlyJungleAsLaner": 0, "goldPerMinute": 283.6745599310898, "hadOpenNexus": 0, "immobilizeAndKillWithAlly": 0, "initialBuffCount": 0, "initialCrabCount": 0, "jungleCsBefore10Minutes": 2, "junglerTakedownsNearDamagedEpicMonster": 0, "kTurretsDestroyedBeforePlatesFall": 0, "kda": 0, "killAfterHiddenWithAlly": 0, "killParticipation": 0, "killedChampTookFullTeamDamageSurvived": 0, "killingSprees": 0, "killsNearEnemyTurret": 0, "killsOnOtherLanesEarlyJungleAsLaner": 0, "killsOnRecentlyHealedByAramPack": 0, "killsUnderOwnTurret": 0, "killsWithHelpFromEpicMonster": 0, "knockEnemyIntoTeamAndKill": 0, "landSkillShotsEarlyGame": 0, "laneMinionsFirst10Minutes": 75, "laningPhaseGoldExpAdvantage": 0, "legendaryCount": 0, "legendaryItemUsed": [6692], "lostAnInhibitor": 0, "maxCsAdvantageOnLaneOpponent": 0, "maxKillDeficit": 0, "maxLevelLeadLaneOpponent": 1, "mejaisFullStackInTime": 0, "moreEnemyJungleThanOpponent": 0, "multiKillOneSpell": 0, "multiTurretRiftHeraldCount": 0, "multikills": 0, "multikillsAfterAggressiveFlash": 0, "outerTurretExecutesBefore10Minutes": 0, "outnumberedKills": 0, "outnumberedNexusKill": 0, "perfectDragonSoulsTaken": 0, "perfectGame": 0, "pickKillWithAlly": 0, "playedChampSelectPosition": 1, "poroExplosions": 0, "quickCleanse": 0, "quickFirstTurret": 0, "quickSoloKills": 0, "riftHeraldTakedowns": 0, "saveAllyFromDeath": 0, "scuttleCrabKills": 0, "skillshotsDodged": 0, "skillshotsHit": 0, "snowballsHit": 0, "soloBaronKills": 0, "soloKills": 0, "stealthWardsPlaced": 4, "survivedSingleDigitHpCount": 0, "survivedThreeImmobilizesInFight": 0, "takedownOnFirstTurret": 0, "takedowns": 0, "takedownsAfterGainingLevelAdvantage": 0, "takedownsBeforeJungleMinionSpawn": 0, "takedownsFirstXMinutes": 0, "takedownsInAlcove": 0, "takedownsInEnemyFountain": 0, "teamBaronKills": 0, "teamDamagePercentage": 0.24336129127095185, "teamElderDragonKills": 0, "teamRiftHeraldKills": 0, "tookLargeDamageSurvived": 0, "turretPlatesTaken": 0, "turretTakedowns": 0, "turretsTakenWithRiftHerald": 0, "twentyMinionsIn3SecondsCount": 0, "twoWardsOneSweeperCount": 0, "unseenRecalls": 0, "visionScoreAdvantageLaneOpponent": -0.32949596643447876, "visionScorePerMinute": 0.5945599358117754, "voidMonsterKill": 3, "wardTakedowns": 0, "wardTakedownsBefore20M": 0, "wardsGuarded": 0}, "champExperience": 7388, "champLevel": 11, "championId": 799, "championName": "Ambessa", "championTransform": 0, "commandPings": 1, "consumablesPurchased": 1, "damageDealtToBuildings": 0, "damageDealtToEpicMonsters": 2381, "damageDealtToObjectives": 2381, "damageDealtToTurrets": 0, "damageSelfMitigated": 9135, "dangerPings": 0, "deaths": 2, "detectorWardsPlaced": 0, "doubleKills": 0, "dragonKills": 0, "eligibleForProgression": true, "enemyMissingPings": 0, "enemyVisionPings": 0, "firstBloodAssist": false, "firstBloodKill": false, "firstTowerAssist": false, "firstTowerKill": false, "gameEndedInEarlySurrender": false, "gameEndedInSurrender": true, "getBackPings": 0, "goldEarned": 4356, "goldSpent": 3900, "holdPings": 0, "individualPosition": "TOP", "inhibitorKills": 0, "inhibitorTakedowns": 0, "inhibitorsLost": 0, "item0": 6692, "item1": 2422, "item2": 1036, "item3": 1054, "item4": 0, "item5": 0, "item6": 3340, "itemsPurchased": 10, "killingSprees": 0, "kills": 0, "lane": "NONE", "largestCriticalStrike": 0, "largestKillingSpree": 0, "largestMultiKill": 0, "longestTimeSpentLiving": 682, "magicDamageDealt": 361, "magicDamageDealtToChampions": 361, "magicDamageTaken": 481, "missions": {"playerScore0": 0, "playerScore1": 0, "playerScore2": 0, "playerScore3": 0, "playerScore4": 0, "playerScore5": 0, "playerScore6": 0, "playerScore7": 0, "playerScore8": 0, "playerScore9": 0, "playerScore10": 0, "playerScore11": 0}, "needVisionPings": 0, "neutralMinionsKilled": 4, "nexusKills": 0, "nexusLost": 1, "nexusTakedowns": 0, "objectivesStolen": 0, "objectivesStolenAssists": 0, "onMyWayPings": 0, "participantId": 1, "pentaKills": 0, "perks": {"statPerks": {"defense": 5001, "flex": 5008, "offense": 5008}, "styles": [{"description": "primaryStyle", "selections": [{"perk": 8437, "var1": 361, "var2": 196, "var3": 0}, {"perk": 8401, "var1": 164, "var2": 0, "var3": 0}, {"perk": 8444, "var1": 783, "var2": 0, "var3": 0}, {"perk": 8451, "var1": 130, "var2": 0, "var3": 0}], "style": 8400}, {"description": "subStyle", "selections": [{"perk": 8304, "var1": 12, "var2": 0, "var3": 0}, {"perk": 8345, "var1": 3, "var2": 0, "var3": 210}], "style": 8300}]}, "physicalDamageDealt": 42580, "physicalDamageDealtToChampions": 6889, "physicalDamageTaken": 11706, "placement": 0, "playerAugment1": 0, "playerAugment2": 0, "playerAugment3": 0, "playerAugment4": 0, "playerAugment5": 0, "playerAugment6": 0, "playerSubteamId": 0, "profileIcon": 5131, "pushPings": 0, "puuid": "pWv9nxzEQ9DqiPT8uuDi2MVKv4Gy01qmQceCfzNNsT9dtugE3rhQMLImjZoicriOGRCXaORzpInwjg", "quadraKills": 0, "retreatPings": 0, "riotIdGameName": "Paclo", "riotIdTagline": "br1", "role": "SUPPORT", "roleBoundItem": 1221, "sightWardsBoughtInGame": 0, "spell1Casts": 88, "spell2Casts": 21, "spell3Casts": 31, "spell4Casts": 2, "subteamPlacement": 0, "summoner1Casts": 2, "summoner1Id": 12, "summoner2Casts": 0, "summoner2Id": 4, "summonerId": "6keDvfrYhYutb0FDOe0yO4yJdAIX2npRf2mrhLXpG4lZCxo", "summonerLevel": 244, "summonerName": "", "teamEarlySurrendered": false, "teamId": 100, "teamPosition": "TOP", "timeCCingOthers": 5, "timePlayed": 921, "totalAllyJungleMinionsKilled": 0, "totalDamageDealt": 42941, "totalDamageDealtToChampions": 7251, "totalDamageShieldedOnTeammates": 0, "totalDamageTaken": 12297, "totalEnemyJungleMinionsKilled": 0, "totalHeal": 2233, "totalHealsOnTeammates": 0, "totalMinionsKilled": 103, "totalTimeCCDealt": 69, "totalTimeSpentDead": 60, "totalUnitsHealed": 1, "tripleKills": 0, "trueDamageDealt": 0, "trueDamageDealtToChampions": 0, "trueDamageTaken": 110, "turretKills": 0, "turretTakedowns": 0, "turretsLost": 3, "unrealKills": 0, "visionClearedPings": 0, "visionScore": 9, "visionWardsBoughtInGame": 0, "wardsKilled": 0, "wardsPlaced": 4, "win": false}, {"PlayerBehavior": {"PlayerBehavior_IsHeroInCombat": 0}, "PlayerScore0": 0, "PlayerScore1": 0, "PlayerScore10": 0, "PlayerScore11": 0, "PlayerScore2": 0, "PlayerScore3": 0, "PlayerScore4": 0, "PlayerScore5": 0, "PlayerScore6": 0, "PlayerScore7": 0, "PlayerScore8": 0, "PlayerScore9": 0, "allInPings": 0, "assistMePings": 2, "assists": 0, "baronKills": 0, "basicPings": 0, "challenges": {"12AssistStreakCount": 0, "HealFromMapSources": 0, "InfernalScalePickup": 0, "SWARM_DefeatAatrox": 0, "SWARM_DefeatBriar": 0, "SWARM_DefeatMiniBosses": 0, "SWARM_EvolveWeapon": 0, "SWARM_Have3Passives": 0, "SWARM_KillEnemy": 0, "SWARM_PickupGold": 0, "SWARM_ReachLevel50": 0, "SWARM_Survive15Min": 0, "SWARM_WinWith5EvolvedWeapons": 0, "abilityUses": 288, "acesBefore15Minutes": 0, "alliedJungleMonsterKills": 57, "baronTakedowns": 0, "blastConeOppositeOpponentCount": 0, "bountyGold": 0, "buffsStolen": 0, "completeSupportQuestInTime": 0, "controlWardsPlaced": 0, "damagePerMinute": 412.1420720530804, "damageTakenOnTeamPercentage": 0.1856366316166214, "dancedWithRiftHerald": 0, "deathsByEnemyChamps": 4, "dodgeSkillShotsSmallWindow": 1, "doubleAces": 0, "dragonTakedowns": 0, "earlyLaningPhaseGoldExpAdvantage": 0, "effectiveHealAndShielding": 0, "elderDragonKillsWithOpposingSoul": 0, "elderDragonMultikills": 0, "enemyChampionImmobilizations": 7, "enemyJungleMonsterKills": 0, "epicMonsterKillsNearEnemyJungler": 0, "epicMonsterKillsWithin30SecondsOfSpawn": 0, "epicMonsterSteals": 0, "epicMonsterStolenWithoutSmite": 0, "firstTurretKilled": 0, "fistBumpParticipation": 0, "flawlessAces": 0, "fullTeamTakedown": 0, "gameLength": 921.399431054, "goldPerMinute": 384.30503163534894, "hadOpenNexus": 0, "immobilizeAndKillWithAlly": 3, "initialBuffCount": 2, "initialCrabCount": 0, "jungleCsBefore10Minutes": 72.00000008940697, "junglerKillsEarlyJungle": 0, "junglerTakedownsNearDamagedEpicMonster": 0, "kTurretsDestroyedBeforePlatesFall": 0, "kda": 0.75, "killAfterHiddenWithAlly": 0, "killParticipation": 0.5, "killedChampTookFullTeamDamageSurvived": 0, "killingSprees": 0, "killsNearEnemyTurret": 1, "killsOnLanersEarlyJungleAsJungler": 3, "killsOnRecentlyHealedByAramPack": 0, "killsUnderOwnTurret": 0, "killsWithHelpFromEpicMonster": 0, "knockEnemyIntoTeamAndKill": 0, "landSkillShotsEarlyGame": 0, "laneMinionsFirst10Minutes": 0, "laningPhaseGoldExpAdvantage": 0, "legendaryCount": 0, "legendaryItemUsed": [6653], "lostAnInhibitor": 0, "maxCsAdvantageOnLaneOpponent": 4, "maxKillDeficit": 0, "maxLevelLeadLaneOpponent": 1, "mejaisFullStackInTime": 0, "moreEnemyJungleThanOpponent": -66.00000011920929, "multiKillOneSpell": 0, "multiTurretRiftHeraldCount": 0, "multikills": 0, "multikillsAfterAggressiveFlash": 0, "outerTurretExecutesBefore10Minutes": 0, "outnumberedKills": 0, "outnumberedNexusKill": 0, "perfectDragonSoulsTaken": 0, "perfectGame": 0, "pickKillWithAlly": 3, "playedChampSelectPosition": 1, "poroExplosions": 0, "quickCleanse": 0, "quickFirstTurret": 0, "quickSoloKills": 0, "riftHeraldTakedowns": 0, "saveAllyFromDeath": 0, "scuttleCrabKills": 2, "skillshotsDodged": 19, "skillshotsHit": 0, "snowballsHit": 0, "soloBaronKills": 0, "soloKills": 0, "stealthWardsPlaced": 5, "survivedSingleDigitHpCount": 0, "survivedThreeImmobilizesInFight": 0, "takedownOnFirstTurret": 0, "takedowns": 3, "takedownsAfterGainingLevelAdvantage": 0, "takedownsBeforeJungleMinionSpawn": 0, "takedownsFirstXMinutes": 3, "takedownsInAlcove": 0, "takedownsInEnemyFountain": 0, "teamBaronKills": 0, "teamDamagePercentage": 0.2124179489074576, "teamElderDragonKills": 0, "teamRiftHeraldKills": 0, "tookLargeDamageSurvived": 0, "turretPlatesTaken": 0, "turretTakedowns": 0, "turretsTakenWithRiftHerald": 0, "twentyMinionsIn3SecondsCount": 0, "twoWardsOneSweeperCount": 0, "unseenRecalls": 0, "visionScoreAdvantageLaneOpponent": -0.2735200524330139, "visionScorePerMinute": 0.7415100397114266, "voidMonsterKill": 3, "wardTakedowns": 0, "wardTakedownsBefore20M": 0, "wardsGuarded": 0}, "champExperience": 6355, "champLevel": 10, "championId": 77, "championName": "Udyr", "championTransform": 0, "commandPings": 2, "consumablesPurchased": 0, "damageDealtToBuildings": 0, "damageDealtToEpicMonsters": 7431, "damageDealtToObjectives": 7431, "damageDealtToTurrets": 0, "damageSelfMitigated": 9534, "dangerPings": 0, "deaths": 4, "detectorWardsPlaced": 0, "doubleKills": 0, "dragonKills": 0, "eligibleForProgression": true, "enemyMissingPings": 7, "enemyVisionPings": 0, "firstBloodAssist": false, "firstBloodKill": true, "firstTowerAssist": false, "firstTowerKill": false, "gameEndedInEarlySurrender": false, "gameEndedInSurrender": true, "getBackPings": 0, "goldEarned": 5901, "goldSpent": 5250, "holdPings": 0, "individualPosition": "JUNGLE", "inhibitorKills": 0, "inhibitorTakedowns": 0, "inhibitorsLost": 0, "item0": 3047, "item1": 1082, "item2": 6653, "item3": 0, "item4": 0, "item5": 2022, "item6": 3340, "itemsPurchased": 12, "killingSprees": 1, "kills": 3, "lane": "NONE", "largestCriticalStrike": 0, "largestKillingSpree": 2, "largestMultiKill": 1, "longestTimeSpentLiving": 351, "magicDamageDealt": 50601, "magicDamageDealtToChampions": 4533, "magicDamageTaken": 4073, "missions": {"playerScore0": 0, "playerScore1": 0, "playerScore2": 0, "playerScore3": 0, "playerScore4": 0, "playerScore5": 0, "playerScore6": 0, "playerScore7": 0, "playerScore8": 0, "playerScore9": 0, "playerScore10": 0, "playerScore11": 0}, "needVisionPings": 0, "neutralMinionsKilled": 106, "nexusKills": 0, "nexusLost": 1, "nexusTakedowns": 0, "objectivesStolen": 0, "objectivesStolenAssists": 0, "onMyWayPings": 13, "participantId": 2, "pentaKills": 0, "perks": {"statPerks": {"defense": 5001, "flex": 5008, "offense": 5008}, "styles": [{"description": "primaryStyle", "selections": [{"perk": 8010, "var1": 72, "var2": 0, "var3": 0}, {"perk": 9111, "var1": 112, "var2": 60, "var3": 0}, {"perk": 9105, "var1": 10, "var2": 0, "var3": 0}, {"perk": 8299, "var1": 254, "var2": 0, "var3": 0}], "style": 8000}, {"description": "subStyle", "selections": [{"perk": 8410, "var1": 34, "var2": 0, "var3": 0}, {"perk": 8313, "var1": 3, "var2": 0, "var3": 0}], "style": 8300}]}, "physicalDamageDealt": 23213, "physicalDamageDealtToChampions": 1770, "physicalDamageTaken": 5855, "placement": 0, "playerAugment1": 0, "playerAugment2": 0, "playerAugment3": 0, "playerAugment4": 0, "playerAugment5": 0, "playerAugment6": 0, "playerSubteamId": 0, "profileIcon": 29, "pushPings": 0, "puuid": "XuksM654VP2A149mMwfsuNn6k3L13SS5ziBllb8IOLIMjD4PpHMmQaf8cIIVLlLEH0-QrgFdxWGZAw", "quadraKills": 0, "retreatPings": 4, "riotIdGameName": "LONDRINA PARANÁ", "riotIdTagline": "043", "role": "SUPPORT", "roleBoundItem": 1209, "sightWardsBoughtInGame": 0, "spell1Casts": 76, "spell2Casts": 52, "spell3Casts": 70, "spell4Casts": 90, "subteamPlacement": 0, "summoner1Casts": 2, "summoner1Id": 4, "summoner2Casts": 9, "summoner2Id": 11, "summonerId": "Y_HHugB2AsdNvOgcndxl_iSt0JkG68-xwiqQ405G_8qe43v2CtfnQVxhLg", "summonerLevel": 97, "summonerName": "", "teamEarlySurrendered": false, "teamId": 100, "teamPosition": "JUNGLE", "timeCCingOthers": 14, "timePlayed": 921, "totalAllyJungleMinionsKilled": 88, "totalDamageDealt": 118622, "totalDamageDealtToChampions": 6329, "totalDamageShieldedOnTeammates": 0, "totalDamageTaken": 10190, "totalEnemyJungleMinionsKilled": 0, "totalHeal": 3287, "totalHealsOnTeammates": 0, "totalMinionsKilled": 1, "totalTimeCCDealt": 1010, "totalTimeSpentDead": 90, "totalUnitsHealed": 1, "tripleKills": 0, "trueDamageDealt": 44807, "trueDamageDealtToChampions": 25, "trueDamageTaken": 260, "turretKills": 0, "turretTakedowns": 0, "turretsLost": 3, "unrealKills": 0, "visionClearedPings": 0, "visionScore": 11, "visionWardsBoughtInGame": 0, "wardsKilled": 0, "wardsPlaced": 5, "win": false}, {"PlayerBehavior": {"PlayerBehavior_IsHeroInCombat": 0}, "PlayerScore0": 0, "PlayerScore1": 0, "PlayerScore10": 0, "PlayerScore11": 0, "PlayerScore2": 0, "PlayerScore3": 0, "PlayerScore4": 0, "PlayerScore5": 0, "PlayerScore6": 0, "PlayerScore7": 0, "PlayerScore8": 0, "PlayerScore9": 0, "allInPings": 0, "assistMePings": 0, "assists": 1, "baronKills": 0, "basicPings": 0, "challenges": {"12AssistStreakCount": 0, "HealFromMapSources": 0, "InfernalScalePickup": 0, "SWARM_DefeatAatrox": 0, "SWARM_DefeatBriar": 0, "SWARM_DefeatMiniBosses": 0, "SWARM_EvolveWeapon": 0, "SWARM_Have3Passives": 0, "SWARM_KillEnemy": 0, "SWARM_PickupGold": 0, "SWARM_ReachLevel50": 0, "SWARM_Survive15Min": 0, "SWARM_WinWith5EvolvedWeapons": 0, "abilityUses": 187, "acesBefore15Minutes": 0, "alliedJungleMonsterKills": 0, "baronTakedowns": 0, "blastConeOppositeOpponentCount": 0, "bountyGold": 316.9162292480469, "buffsStolen": 0, "completeSupportQuestInTime": 0, "controlWardsPlaced": 0, "damagePerMinute": 490.7026733729359, "damageTakenOnTeamPercentage": 0.29961405138697605, "dancedWithRiftHerald": 0, "deathsByEnemyChamps": 5, "dodgeSkillShotsSmallWindow": 54, "doubleAces": 0, "dragonTakedowns": 0, "earlyLaningPhaseGoldExpAdvantage": 1, "effectiveHealAndShielding": 0, "elderDragonKillsWithOpposingSoul": 0, "elderDragonMultikills": 0, "enemyChampionImmobilizations": 13, "enemyJungleMonsterKills": 0, "epicMonsterKillsNearEnemyJungler": 0, "epicMonsterKillsWithin30SecondsOfSpawn": 0, "epicMonsterSteals": 0, "epicMonsterStolenWithoutSmite": 0, "firstTurretKilled": 0, "fistBumpParticipation": 0, "flawlessAces": 0, "fullTeamTakedown": 0, "gameLength": 921.399431054, "getTakedownsInAllLanesEarlyJungleAsLaner": 0, "goldPerMinute": 358.1213229377243, "hadOpenNexus": 0, "immobilizeAndKillWithAlly": 0, "initialBuffCount": 0, "initialCrabCount": 0, "jungleCsBefore10Minutes": 0, "junglerTakedownsNearDamagedEpicMonster": 0, "kTurretsDestroyedBeforePlatesFall": 0, "kda": 0.6, "killAfterHiddenWithAlly": 0, "killParticipation": 0.5, "killedChampTookFullTeamDamageSurvived": 0, "killingSprees": 0, "killsNearEnemyTurret": 1, "killsOnOtherLanesEarlyJungleAsLaner": 0, "killsOnRecentlyHealedByAramPack": 0, "killsUnderOwnTurret": 0, "killsWithHelpFromEpicMonster": 0, "knockEnemyIntoTeamAndKill": 0, "landSkillShotsEarlyGame": 5, "laneMinionsFirst10Minutes": 88, "laningPhaseGoldExpAdvantage": 0, "legendaryCount": 0, "legendaryItemUsed": [3153], "lostAnInhibitor": 0, "maxCsAdvantageOnLaneOpponent": 28, "maxKillDeficit": 0, "maxLevelLeadLaneOpponent": 1, "mejaisFullStackInTime": 0, "moreEnemyJungleThanOpponent": 0, "multiKillOneSpell": 0, "multiTurretRiftHeraldCount": 0, "multikills": 0, "multikillsAfterAggressiveFlash": 0, "outerTurretExecutesBefore10Minutes": 0, "outnumberedKills": 0, "outnumberedNexusKill": 0, "perfectDragonSoulsTaken": 0, "perfectGame": 0, "pickKillWithAlly": 1, "playedChampSelectPosition": 1, "poroExplosions": 0, "quickCleanse": 0, "quickFirstTurret": 0, "quickSoloKills": 0, "riftHeraldTakedowns": 0, "saveAllyFromDeath": 0, "scuttleCrabKills": 0, "skillshotsDodged": 329, "skillshotsHit": 10, "snowballsHit": 0, "soloBaronKills": 0, "soloKills": 2, "stealthWardsPlaced": 4, "survivedSingleDigitHpCount": 0, "survivedThreeImmobilizesInFight": 26, "takedownOnFirstTurret": 0, "takedowns": 3, "takedownsAfterGainingLevelAdvantage": 0, "takedownsBeforeJungleMinionSpawn": 0, "takedownsFirstXMinutes": 3, "takedownsInAlcove": 0, "takedownsInEnemyFountain": 0, "teamBaronKills": 0, "teamDamagePercentage": 0.25290806852608994, "teamElderDragonKills": 0, "teamRiftHeraldKills": 0, "tookLargeDamageSurvived": 0, "turretPlatesTaken": 1, "turretTakedowns": 0, "turretsTakenWithRiftHerald": 0, "twentyMinionsIn3SecondsCount": 0, "twoWardsOneSweeperCount": 0, "unseenRecalls": 0, "visionScoreAdvantageLaneOpponent": -0.460734486579895, "visionScorePerMinute": 0.2841193784163788, "voidMonsterKill": 0, "wardTakedowns": 0, "wardTakedownsBefore20M": 0, "wardsGuarded": 0}, "champExperience": 7150, "champLevel": 10, "championId": 777, "championName": "Yone", "championTransform": 0, "commandPings": 5, "consumablesPurchased": 1, "damageDealtToBuildings": 638, "damageDealtToEpicMonsters": 0, "damageDealtToObjectives": 638, "damageDealtToTurrets": 638, "damageSelfMitigated": 8686, "dangerPings": 0, "deaths": 5, "detectorWardsPlaced": 0, "doubleKills": 0, "dragonKills": 0, "eligibleForProgression": true, "enemyMissingPings": 0, "enemyVisionPings": 0, "firstBloodAssist": false, "firstBloodKill": false, "firstTowerAssist": false, "firstTowerKill": false, "gameEndedInEarlySurrender": false, "gameEndedInSurrender": true, "getBackPings": 0, "goldEarned": 5499, "goldSpent": 5300, "holdPings": 0, "individualPosition": "MIDDLE", "inhibitorKills": 0, "inhibitorTakedowns": 0, "inhibitorsLost": 0, "item0": 3172, "item1": 1036, "item2": 3153, "item3": 1054, "item4": 0, "item5": 0, "item6": 3340, "itemsPurchased": 12, "killingSprees": 0, "kills": 2, "lane": "NONE", "largestCriticalStrike": 0, "largestKillingSpree": 0, "largestMultiKill": 1, "longestTimeSpentLiving": 611, "magicDamageDealt": 4826, "magicDamageDealtToChampions": 898, "magicDamageTaken": 11343, "missions": {"playerScore0": 0, "playerScore1": 0, "playerScore2": 0, "playerScore3": 0, "playerScore4": 0, "playerScore5": 0, "playerScore6": 0, "playerScore7": 0, "playerScore8": 0, "playerScore9": 0, "playerScore10": 0, "playerScore11": 0}, "needVisionPings": 0, "neutralMinionsKilled": 0, "nexusKills": 0, "nexusLost": 1, "nexusTakedowns": 0, "objectivesStolen": 0, "objectivesStolenAssists": 0, "onMyWayPings": 1, "participantId": 3, "pentaKills": 0, "perks": {"statPerks": {"defense": 5011, "flex": 5008, "offense": 5005}, "styles": [{"description": "primaryStyle", "selections": [{"perk": 8008, "var1": 183, "var2": 183, "var3": 0}, {"perk": 9101, "var1": 340, "var2": 0, "var3": 0}, {"perk": 9104, "var1": 0, "var2": 0, "var3": 0}, {"perk": 8299, "var1": 382, "var2": 0, "var3": 0}], "style": 8000}, {"description": "subStyle", "selections": [{"perk": 8451, "var1": 118, "var2": 0, "var3": 0}, {"perk": 8444, "var1": 1241, "var2": 0, "var3": 0}], "style": 8400}]}, "physicalDamageDealt": 40850, "physicalDamageDealtToChampions": 5452, "physicalDamageTaken": 4385, "placement": 0, "playerAugment1": 0, "playerAugment2": 0, "playerAugment3": 0, "playerAugment4": 0, "playerAugment5": 0, "playerAugment6": 0, "playerSubteamId": 0, "profileIcon": 5871, "pushPings": 0, "puuid": "XGmv-8vX9SJcwKVfpfWjcPFerisOXJ6WTx8t5rEK-QklpDM6WIoa2HMd2-GKKU6WY8VkF0m7oIe-kA", "quadraKills": 0, "retreatPings": 2, "riotIdGameName": "NEADZ", "riotIdTagline": "898", "role": "SUPPORT", "roleBoundItem": 1206, "sightWardsBoughtInGame": 0, "spell1Casts": 112, "spell2Casts": 35, "spell3Casts": 36, "spell4Casts": 4, "subteamPlacement": 0, "summoner1Casts": 1, "summoner1Id": 4, "summoner2Casts": 1, "summoner2Id": 12, "summonerId": "EyZKiEbWBprOlp4J4_MpGM_ixEhxzFqIa_7FoBa4IUnMc1U", "summonerLevel": 500, "summonerName": "", "teamEarlySurrendered": false, "teamId": 100, "teamPosition": "MIDDLE", "timeCCingOthers": 10, "timePlayed": 921, "totalAllyJungleMinionsKilled": 0, "totalDamageDealt": 47442, "totalDamageDealtToChampions": 7535, "totalDamageShieldedOnTeammates": 0, "totalDamageTaken": 16446, "totalEnemyJungleMinionsKilled": 0, "totalHeal": 1867, "totalHealsOnTeammates": 0, "totalMinionsKilled": 112, "totalTimeCCDealt": 71, "totalTimeSpentDead": 116, "totalUnitsHealed": 1, "tripleKills": 0, "trueDamageDealt": 1765, "trueDamageDealtToChampions": 1184, "trueDamageTaken": 717, "turretKills": 0, "turretTakedowns": 0, "turretsLost": 3, "unrealKills": 0, "visionClearedPings": 0, "visionScore": 4, "visionWardsBoughtInGame": 0, "wardsKilled": 0, "wardsPlaced": 4, "win": false}, {"PlayerBehavior": {"PlayerBehavior_IsHeroInCombat": 0}, "PlayerScore0": 0, "PlayerScore1": 0, "PlayerScore10": 0, "PlayerScore11": 0, "PlayerScore2": 0, "PlayerScore3": 0, "PlayerScore4": 0, "PlayerScore5": 0, "PlayerScore6": 0, "PlayerScore7": 0, "PlayerScore8": 0, "PlayerScore9": 0, "allInPings": 0, "assistMePings": 2, "assists": 1, "baronKills": 0, "basicPings": 0, "challenges": {"12AssistStreakCount": 0, "HealFromMapSources": 0, "InfernalScalePickup": 0, "SWARM_DefeatAatrox": 0, "SWARM_DefeatBriar": 0, "SWARM_DefeatMiniBosses": 0, "SWARM_EvolveWeapon": 0, "SWARM_Have3Passives": 0, "SWARM_KillEnemy": 0, "SWARM_PickupGold": 0, "SWARM_ReachLevel50": 0, "SWARM_Survive15Min": 0, "SWARM_WinWith5EvolvedWeapons": 0, "abilityUses": 83, "acesBefore15Minutes": 0, "alliedJungleMonsterKills": 0, "baronTakedowns": 0, "blastConeOppositeOpponentCount": 0, "bountyGold": 0, "buffsStolen": 0, "completeSupportQuestInTime": 0, "controlWardsPlaced": 3, "damagePerMinute": 313.81395332110753, "damageTakenOnTeamPercentage": 0.11500032960793788, "dancedWithRiftHerald": 0, "deathsByEnemyChamps": 2, "dodgeSkillShotsSmallWindow": 0, "doubleAces": 0, "dragonTakedowns": 0, "earlyLaningPhaseGoldExpAdvantage": 0, "effectiveHealAndShielding": 0, "elderDragonKillsWithOpposingSoul": 0, "elderDragonMultikills": 0, "enemyChampionImmobilizations": 3, "enemyJungleMonsterKills": 0, "epicMonsterKillsNearEnemyJungler": 0, "epicMonsterKillsWithin30SecondsOfSpawn": 0, "epicMonsterSteals": 0, "epicMonsterStolenWithoutSmite": 0, "firstTurretKilled": 0, "fistBumpParticipation": 0, "flawlessAces": 0, "fullTeamTakedown": 0, "gameLength": 921.399431054, "getTakedownsInAllLanesEarlyJungleAsLaner": 0, "goldPerMinute": 302.912386718082, "hadOpenNexus": 0, "immobilizeAndKillWithAlly": 1, "initialBuffCount": 0, "initialCrabCount": 0, "jungleCsBefore10Minutes": 0, "junglerTakedownsNearDamagedEpicMonster": 0, "kTurretsDestroyedBeforePlatesFall": 0, "kda": 1, "killAfterHiddenWithAlly": 0, "killParticipation": 0.3333333333333333, "killedChampTookFullTeamDamageSurvived": 0, "killingSprees": 0, "killsNearEnemyTurret": 0, "killsOnOtherLanesEarlyJungleAsLaner": 0, "killsOnRecentlyHealedByAramPack": 0, "killsUnderOwnTurret": 0, "killsWithHelpFromEpicMonster": 0, "knockEnemyIntoTeamAndKill": 0, "landSkillShotsEarlyGame": 19, "laneMinionsFirst10Minutes": 62, "laningPhaseGoldExpAdvantage": 0, "legendaryCount": 0, "legendaryItemUsed": [], "lostAnInhibitor": 0, "maxCsAdvantageOnLaneOpponent": 0, "maxKillDeficit": 0, "maxLevelLeadLaneOpponent": 1, "mejaisFullStackInTime": 0, "moreEnemyJungleThanOpponent": 0, "multiKillOneSpell": 0, "multiTurretRiftHeraldCount": 0, "multikills": 0, "multikillsAfterAggressiveFlash": 0, "outerTurretExecutesBefore10Minutes": 0, "outnumberedKills": 0, "outnumberedNexusKill": 0, "perfectDragonSoulsTaken": 0, "perfectGame": 0, "pickKillWithAlly": 2, "playedChampSelectPosition": 1, "poroExplosions": 0, "quickCleanse": 0, "quickFirstTurret": 0, "quickSoloKills": 0, "riftHeraldTakedowns": 0, "saveAllyFromDeath": 0, "scuttleCrabKills": 0, "skillshotsDodged": 15, "skillshotsHit": 29, "snowballsHit": 0, "soloBaronKills": 0, "soloKills": 0, "stealthWardsPlaced": 6, "survivedSingleDigitHpCount": 0, "survivedThreeImmobilizesInFight": 0, "takedownOnFirstTurret": 0, "takedowns": 2, "takedownsAfterGainingLevelAdvantage": 0, "takedownsBeforeJungleMinionSpawn": 0, "takedownsFirstXMinutes": 2, "takedownsInAlcove": 0, "takedownsInEnemyFountain": 0, "teamBaronKills": 0, "teamDamagePercentage": 0.1617396544132119, "teamElderDragonKills": 0, "teamRiftHeraldKills": 0, "tookLargeDamageSurvived": 0, "turretPlatesTaken": 0, "turretTakedowns": 0, "turretsTakenWithRiftHerald": 0, "twentyMinionsIn3SecondsCount": 0, "twoWardsOneSweeperCount": 0, "unseenRecalls": 0, "visionScoreAdvantageLaneOpponent": 1.2624866962432861, "visionScorePerMinute": 1.1713828846224295, "voidMonsterKill": 0, "wardTakedowns": 2, "wardTakedownsBefore20M": 2, "wardsGuarded": 0}, "champExperience": 5944, "champLevel": 9, "championId": 498, "championName": "Xayah", "championTransform": 0, "commandPings": 1, "consumablesPurchased": 4, "damageDealtToBuildings": 0, "damageDealtToEpicMonsters": 19, "damageDealtToObjectives": 19, "damageDealtToTurrets": 0, "damageSelfMitigated": 2815, "dangerPings": 0, "deaths": 2, "detectorWardsPlaced": 3, "doubleKills": 0, "dragonKills": 0, "eligibleForProgression": true, "enemyMissingPings": 7, "enemyVisionPings": 3, "firstBloodAssist": false, "firstBloodKill": false, "firstTowerAssist": false, "firstTowerKill": false, "gameEndedInEarlySurrender": false, "gameEndedInSurrender": true, "getBackPings": 0, "goldEarned": 4651, "goldSpent": 4375, "holdPings": 0, "individualPosition": "BOTTOM", "inhibitorKills": 0, "inhibitorTakedowns": 0, "inhibitorsLost": 0, "item0": 1055, "item1": 3006, "item2": 3133, "item3": 1018, "item4": 0, "item5": 3057, "item6": 3340, "itemsPurchased": 15, "killingSprees": 0, "kills": 1, "lane": "NONE", "largestCriticalStrike": 0, "largestKillingSpree": 0, "largestMultiKill": 1, "longestTimeSpentLiving": 188, "magicDamageDealt": 39, "magicDamageDealtToChampions": 0, "magicDamageTaken": 2051, "missions": {"playerScore0": 0, "playerScore1": 0, "playerScore2": 0, "playerScore3": 0, "playerScore4": 0, "playerScore5": 0, "playerScore6": 0, "playerScore7": 0, "playerScore8": 0, "playerScore9": 0, "playerScore10": 0, "playerScore11": 0}, "needVisionPings": 0, "neutralMinionsKilled": 0, "nexusKills": 0, "nexusLost": 1, "nexusTakedowns": 0, "objectivesStolen": 0, "objectivesStolenAssists": 0, "onMyWayPings": 3, "participantId": 4, "pentaKills": 0, "perks": {"statPerks": {"defense": 5001, "flex": 5008, "offense": 5005}, "styles": [{"description": "primaryStyle", "selections": [{"perk": 8008, "var1": 16, "var2": 16, "var3": 0}, {"perk": 8009, "var1": 227, "var2": 0, "var3": 0}, {"perk": 9103, "var1": 0, "var2": 0, "var3": 0}, {"perk": 8017, "var1": 289, "var2": 0, "var3": 0}], "style": 8000}, {"description": "subStyle", "selections": [{"perk": 8321, "var1": 0, "var2": 0, "var3": 0}, {"perk": 8313, "var1": 3, "var2": 0, "var3": 0}], "style": 8300}]}, "physicalDamageDealt": 46334, "physicalDamageDealtToChampions": 4819, "physicalDamageTaken": 4260, "placement": 0, "playerAugment1": 0, "playerAugment2": 0, "playerAugment3": 0, "playerAugment4": 0, "playerAugment5": 0, "playerAugment6": 0, "playerSubteamId": 0, "profileIcon": 7019, "pushPings": 0, "puuid": "wCOAXejv6qFJ8CfuqJO7LL5X56Dr4Bdb6MVNfDkj03HaZoIDGkSMxGRpZUC8uIN0UXSPMNAr1D30Nw", "quadraKills": 0, "retreatPings": 6, "riotIdGameName": "BBN MatMac", "riotIdTagline": "8632", "role": "SUPPORT", "roleBoundItem": 1202, "sightWardsBoughtInGame": 0, "spell1Casts": 41, "spell2Casts": 18, "spell3Casts": 24, "spell4Casts": 0, "subteamPlacement": 0, "summoner1Casts": 1, "summoner1Id": 4, "summoner2Casts": 2, "summoner2Id": 21, "summonerId": "mQQOdOsMszFvGmthw8-fvpydsHt9wPQeZh17WIvLwTLqBw", "summonerLevel": 740, "summonerName": "", "teamEarlySurrendered": false, "teamId": 100, "teamPosition": "BOTTOM", "timeCCingOthers": 4, "timePlayed": 921, "totalAllyJungleMinionsKilled": 0, "totalDamageDealt": 46383, "totalDamageDealtToChampions": 4819, "totalDamageShieldedOnTeammates": 0, "totalDamageTaken": 6312, "totalEnemyJungleMinionsKilled": 0, "totalHeal": 1562, "totalHealsOnTeammates": 0, "totalMinionsKilled": 106, "totalTimeCCDealt": 4, "totalTimeSpentDead": 24, "totalUnitsHealed": 1, "tripleKills": 0, "trueDamageDealt": 10, "trueDamageDealtToChampions": 0, "trueDamageTaken": 0, "turretKills": 0, "turretTakedowns": 0, "turretsLost": 3, "unrealKills": 0, "visionClearedPings": 0, "visionScore": 17, "visionWardsBoughtInGame": 3, "wardsKilled": 2, "wardsPlaced": 9, "win": false}, {"PlayerBehavior": {"PlayerBehavior_IsHeroInCombat": 0}, "PlayerScore0": 0, "PlayerScore1": 0, "PlayerScore10": 0, "PlayerScore11": 0, "PlayerScore2": 0, "PlayerScore3": 0, "PlayerScore4": 0, "PlayerScore5": 0, "PlayerScore6": 0, "PlayerScore7": 0, "PlayerScore8": 0, "PlayerScore9": 0, "allInPings": 1, "assistMePings": 0, "assists": 4, "baronKills": 0, "basicPings": 0, "challenges": {"12AssistStreakCount": 0, "HealFromMapSources": 0, "InfernalScalePickup": 0, "SWARM_DefeatAatrox": 0, "SWARM_DefeatBriar": 0, "SWARM_DefeatMiniBosses": 0, "SWARM_EvolveWeapon": 0, "SWARM_Have3Passives": 0, "SWARM_KillEnemy": 0, "SWARM_PickupGold": 0, "SWARM_ReachLevel50": 0, "SWARM_Survive15Min": 0, "SWARM_WinWith5EvolvedWeapons": 0, "abilityUses": 55, "acesBefore15Minutes": 0, "alliedJungleMonsterKills": 0, "baronTakedowns": 0, "blastConeOppositeOpponentCount": 0, "bountyGold": 0, "buffsStolen": 0, "completeSupportQuestInTime": 1, "controlWardTimeCoverageInRiverOrEnemyHalf": 0.19618490040982672, "controlWardsPlaced": 3, "damagePerMinute": 251.40295430562756, "damageTakenOnTeamPercentage": 0.17572384300386537, "dancedWithRiftHerald": 0, "deathsByEnemyChamps": 4, "dodgeSkillShotsSmallWindow": 5, "doubleAces": 0, "dragonTakedowns": 0, "earlyLaningPhaseGoldExpAdvantage": 0, "effectiveHealAndShielding": 466, "elderDragonKillsWithOpposingSoul": 0, "elderDragonMultikills": 0, "enemyChampionImmobilizations": 29, "enemyJungleMonsterKills": 0, "epicMonsterKillsNearEnemyJungler": 0, "epicMonsterKillsWithin30SecondsOfSpawn": 0, "epicMonsterSteals": 0, "epicMonsterStolenWithoutSmite": 0, "firstTurretKilled": 0, "fistBumpParticipation": 0, "flawlessAces": 0, "fullTeamTakedown": 0, "gameLength": 921.399431054, "getTakedownsInAllLanesEarlyJungleAsLaner": 0, "goldPerMinute": 250.4178486601729, "hadOpenNexus": 0, "immobilizeAndKillWithAlly": 4, "initialBuffCount": 0, "initialCrabCount": 0, "jungleCsBefore10Minutes": 0, "junglerTakedownsNearDamagedEpicMonster": 0, "kTurretsDestroyedBeforePlatesFall": 0, "kda": 1, "killAfterHiddenWithAlly": 0, "killParticipation": 0.6666666666666666, "killedChampTookFullTeamDamageSurvived": 0, "killingSprees": 0, "killsNearEnemyTurret": 0, "killsOnOtherLanesEarlyJungleAsLaner": 0, "killsOnRecentlyHealedByAramPack": 0, "killsUnderOwnTurret": 0, "killsWithHelpFromEpicMonster": 0, "knockEnemyIntoTeamAndKill": 0, "landSkillShotsEarlyGame": 6, "laneMinionsFirst10Minutes": 9, "laningPhaseGoldExpAdvantage": 0, "legendaryCount": 0, "legendaryItemUsed": [3869, 3050], "lostAnInhibitor": 0, "maxCsAdvantageOnLaneOpponent": 2, "maxKillDeficit": 0, "maxLevelLeadLaneOpponent": 1, "mejaisFullStackInTime": 0, "moreEnemyJungleThanOpponent": 0, "multiKillOneSpell": 0, "multiTurretRiftHeraldCount": 0, "multikills": 0, "multikillsAfterAggressiveFlash": 0, "outerTurretExecutesBefore10Minutes": 0, "outnumberedKills": 0, "outnumberedNexusKill": 0, "perfectDragonSoulsTaken": 0, "perfectGame": 0, "pickKillWithAlly": 4, "playedChampSelectPosition": 1, "poroExplosions": 0, "quickCleanse": 0, "quickFirstTurret": 0, "quickSoloKills": 0, "riftHeraldTakedowns": 0, "saveAllyFromDeath": 0, "scuttleCrabKills": 0, "skillshotsDodged": 44, "skillshotsHit": 13, "snowballsHit": 0, "soloBaronKills": 0, "soloKills": 0, "stealthWardsPlaced": 10, "survivedSingleDigitHpCount": 0, "survivedThreeImmobilizesInFight": 0, "takedownOnFirstTurret": 0, "takedowns": 4, "takedownsAfterGainingLevelAdvantage": 0, "takedownsBeforeJungleMinionSpawn": 0, "takedownsFirstXMinutes": 4, "takedownsInAlcove": 0, "takedownsInEnemyFountain": 0, "teamBaronKills": 0, "teamDamagePercentage": 0.12957303688228872, "teamElderDragonKills": 0, "teamRiftHeraldKills": 0, "tookLargeDamageSurvived": 0, "turretPlatesTaken": 0, "turretTakedowns": 0, "turretsTakenWithRiftHerald": 0, "twentyMinionsIn3SecondsCount": 0, "twoWardsOneSweeperCount": 0, "unseenRecalls": 0, "visionScoreAdvantageLaneOpponent": -0.33877211809158325, "visionScorePerMinute": 1.5272336238236357, "voidMonsterKill": 0, "wardTakedowns": 3, "wardTakedownsBefore20M": 3, "wardsGuarded": 0}, "champExperience": 3661, "champLevel": 7, "championId": 89, "championName": "Leona", "championTransform": 0, "commandPings": 11, "consumablesPurchased": 5, "damageDealtToBuildings": 0, "damageDealtToEpicMonsters": 0, "damageDealtToObjectives": 0, "damageDealtToTurrets": 0, "damageSelfMitigated": 8559, "dangerPings": 0, "deaths": 4, "detectorWardsPlaced": 3, "doubleKills": 0, "dragonKills": 0, "eligibleForProgression": true, "enemyMissingPings": 0, "enemyVisionPings": 1, "firstBloodAssist": true, "firstBloodKill": false, "firstTowerAssist": false, "firstTowerKill": false, "gameEndedInEarlySurrender": false, "gameEndedInSurrender": true, "getBackPings": 0, "goldEarned": 3845, "goldSpent": 3190, "holdPings": 0, "individualPosition": "UTILITY", "inhibitorKills": 0, "inhibitorTakedowns": 0, "inhibitorsLost": 0, "item0": 1001, "item1": 3050, "item2": 3869, "item3": 0, "item4": 0, "item5": 0, "item6": 3364, "itemsPurchased": 14, "killingSprees": 0, "kills": 0, "lane": "NONE", "largestCriticalStrike": 0, "largestKillingSpree": 0, "largestMultiKill": 0, "longestTimeSpentLiving": 395, "magicDamageDealt": 3991, "magicDamageDealtToChampions": 2448, "magicDamageTaken": 3798, "missions": {"playerScore0": 0, "playerScore1": 0, "playerScore2": 0, "playerScore3": 0, "playerScore4": 0, "playerScore5": 0, "playerScore6": 0, "playerScore7": 0, "playerScore8": 0, "playerScore9": 0, "playerScore10": 0, "playerScore11": 0}, "needVisionPings": 0, "neutralMinionsKilled": 0, "nexusKills": 0, "nexusLost": 1, "nexusTakedowns": 0, "objectivesStolen": 0, "objectivesStolenAssists": 0, "onMyWayPings": 11, "participantId": 5, "pentaKills": 0, "perks": {"statPerks": {"defense": 5011, "flex": 5010, "offense": 5007}, "styles": [{"description": "primaryStyle", "selections": [{"perk": 8439, "var1": 336, "var2": 327, "var3": 0}, {"perk": 8463, "var1": 331, "var2": 0, "var3": 0}, {"perk": 8473, "var1": 301, "var2": 0, "var3": 0}, {"perk": 8242, "var1": 26, "var2": 0, "var3": 0}], "style": 8400}, {"description": "subStyle", "selections": [{"perk": 8306, "var1": 3, "var2": 0, "var3": 0}, {"perk": 8347, "var1": 0, "var2": 0, "var3": 0}], "style": 8300}]}, "physicalDamageDealt": 3314, "physicalDamageDealtToChampions": 1412, "physicalDamageTaken": 5672, "placement": 0, "playerAugment1": 0, "playerAugment2": 0, "playerAugment3": 0, "playerAugment4": 0, "playerAugment5": 0, "playerAugment6": 0, "playerSubteamId": 0, "profileIcon": 7035, "pushPings": 0, "puuid": "wcWDFtQRdWqCboDhrPT_ZTTNEgWXSJ8KNoakADocffHFS871blVGNcI2Gh7n7QU3kGZOIfuzCVFfgw", "quadraKills": 0, "retreatPings": 2, "riotIdGameName": "Zelda", "riotIdTagline": "ZZZZ", "role": "SUPPORT", "roleBoundItem": 1208, "sightWardsBoughtInGame": 0, "spell1Casts": 22, "spell2Casts": 13, "spell3Casts": 16, "spell4Casts": 4, "subteamPlacement": 0, "summoner1Casts": 4, "summoner1Id": 7, "summoner2Casts": 6, "summoner2Id": 4, "summonerId": "m4bGSUD618U2zGvCgpWw40xgzdRtQXV0gC946LxW8A5VsTpO0kFinAXg9A", "summonerLevel": 108, "summonerName": "", "teamEarlySurrendered": false, "teamId": 100, "teamPosition": "UTILITY", "timeCCingOthers": 25, "timePlayed": 921, "totalAllyJungleMinionsKilled": 0, "totalDamageDealt": 8659, "totalDamageDealtToChampions": 3860, "totalDamageShieldedOnTeammates": 0, "totalDamageTaken": 9646, "totalEnemyJungleMinionsKilled": 0, "totalHeal": 1558, "totalHealsOnTeammates": 466, "totalMinionsKilled": 17, "totalTimeCCDealt": 41, "totalTimeSpentDead": 42, "totalUnitsHealed": 4, "tripleKills": 0, "trueDamageDealt": 1354, "trueDamageDealtToChampions": 0, "trueDamageTaken": 175, "turretKills": 0, "turretTakedowns": 0, "turretsLost": 3, "unrealKills": 0, "visionClearedPings": 0, "visionScore": 23, "visionWardsBoughtInGame": 3, "wardsKilled": 3, "wardsPlaced": 13, "win": false}, {"PlayerBehavior": {"PlayerBehavior_IsHeroInCombat": 0}, "PlayerScore0": 0, "PlayerScore1": 0, "PlayerScore10": 0, "PlayerScore11": 0, "PlayerScore2": 0, "PlayerScore3": 0, "PlayerScore4": 0, "PlayerScore5": 0, "PlayerScore6": 0, "PlayerScore7": 0, "PlayerScore8": 0, "PlayerScore9": 0, "allInPings": 0, "assistMePings": 0, "assists": 0, "baronKills": 0, "basicPings": 0, "challenges": {"12AssistStreakCount": 0, "HealFromMapSources": 0, "InfernalScalePickup": 0, "SWARM_DefeatAatrox": 0, "SWARM_DefeatBriar": 0, "SWARM_DefeatMiniBosses": 0, "SWARM_EvolveWeapon": 0, "SWARM_Have3Passives": 0, "SWARM_KillEnemy": 0, "SWARM_PickupGold": 0, "SWARM_ReachLevel50": 0, "SWARM_Survive15Min": 0, "SWARM_WinWith5EvolvedWeapons": 0, "abilityUses": 119, "acesBefore15Minutes": 0, "alliedJungleMonsterKills": 0, "baronTakedowns": 0, "blastConeOppositeOpponentCount": 0, "bountyGold": 0, "buffsStolen": 0, "completeSupportQuestInTime": 0, "controlWardsPlaced": 0, "damagePerMinute": 841.1050884994308, "damageTakenOnTeamPercentage": 0.2549347938362991, "dancedWithRiftHerald": 0, "deathsByEnemyChamps": 0, "dodgeSkillShotsSmallWindow": 0, "doubleAces": 0, "dragonTakedowns": 0, "earlyLaningPhaseGoldExpAdvantage": 0, "effectiveHealAndShielding": 0, "elderDragonKillsWithOpposingSoul": 0, "elderDragonMultikills": 0, "enemyChampionImmobilizations": 15, "enemyJungleMonsterKills": 0, "epicMonsterKillsNearEnemyJungler": 0, "epicMonsterKillsWithin30SecondsOfSpawn": 0, "epicMonsterSteals": 0, "epicMonsterStolenWithoutSmite": 0, "firstTurretKilled": 1, "firstTurretKilledTime": 806.4253690620001, "fistBumpParticipation": 0, "flawlessAces": 0, "fullTeamTakedown": 0, "gameLength": 921.399431054, "getTakedownsInAllLanesEarlyJungleAsLaner": 0, "goldPerMinute": 476.2189940298912, "hadOpenNexus": 0, "immobilizeAndKillWithAlly": 0, "initialBuffCount": 0, "initialCrabCount": 0, "jungleCsBefore10Minutes": 0, "junglerTakedownsNearDamagedEpicMonster": 0, "kTurretsDestroyedBeforePlatesFall": 1, "kda": 3, "killAfterHiddenWithAlly": 0, "killParticipation": 0.17647058823529413, "killedChampTookFullTeamDamageSurvived": 0, "killingSprees": 1, "killsNearEnemyTurret": 2, "killsOnOtherLanesEarlyJungleAsLaner": 0, "killsOnRecentlyHealedByAramPack": 0, "killsUnderOwnTurret": 0, "killsWithHelpFromEpicMonster": 0, "knockEnemyIntoTeamAndKill": 0, "landSkillShotsEarlyGame": 0, "laneMinionsFirst10Minutes": 97, "laningPhaseGoldExpAdvantage": 1, "legendaryCount": 0, "legendaryItemUsed": [6692], "lostAnInhibitor": 0, "maxCsAdvantageOnLaneOpponent": 52, "maxKillDeficit": 3, "maxLevelLeadLaneOpponent": 3, "mejaisFullStackInTime": 0, "moreEnemyJungleThanOpponent": 0, "multiKillOneSpell": 0, "multiTurretRiftHeraldCount": 0, "multikills": 0, "multikillsAfterAggressiveFlash": 0, "outerTurretExecutesBefore10Minutes": 0, "outnumberedKills": 1, "outnumberedNexusKill": 0, "perfectDragonSoulsTaken": 0, "perfectGame": 0, "pickKillWithAlly": 0, "playedChampSelectPosition": 1, "poroExplosions": 0, "quickCleanse": 0, "quickFirstTurret": 0, "quickSoloKills": 0, "riftHeraldTakedowns": 0, "saveAllyFromDeath": 0, "scuttleCrabKills": 0, "skillshotsDodged": 0, "skillshotsHit": 0, "snowballsHit": 0, "soloBaronKills": 0, "soloKills": 3, "stealthWardsPlaced": 5, "survivedSingleDigitHpCount": 0, "survivedThreeImmobilizesInFight": 2, "takedownOnFirstTurret": 1, "takedowns": 3, "takedownsAfterGainingLevelAdvantage": 0, "takedownsBeforeJungleMinionSpawn": 0, "takedownsFirstXMinutes": 3, "takedownsInAlcove": 0, "takedownsInEnemyFountain": 0, "teamBaronKills": 0, "teamDamagePercentage": 0.27583587834476075, "teamElderDragonKills": 0, "teamRiftHeraldKills": 0, "tookLargeDamageSurvived": 0, "turretPlatesTaken": 6, "turretTakedowns": 1, "turretsTakenWithRiftHerald": 0, "twentyMinionsIn3SecondsCount": 0, "twoWardsOneSweeperCount": 0, "unseenRecalls": 0, "visionScoreAdvantageLaneOpponent": 0.4914153814315796, "visionScorePerMinute": 0.8867358281723948, "voidMonsterKill": 0, "wardTakedowns": 1, "wardTakedownsBefore20M": 1, "wardsGuarded": 0}, "champExperience": 10917, "champLevel": 13, "championId": 58, "championName": "Renekton", "championTransform": 0, "commandPings": 0, "consumablesPurchased": 1, "damageDealtToBuildings": 6157, "damageDealtToEpicMonsters": 0, "damageDealtToObjectives": 6157, "damageDealtToTurrets": 6157, "damageSelfMitigated": 10480, "dangerPings": 0, "deaths": 0, "detectorWardsPlaced": 0, "doubleKills": 0, "dragonKills": 0, "eligibleForProgression": true, "enemyMissingPings": 2, "enemyVisionPings": 3, "firstBloodAssist": false, "firstBloodKill": false, "firstTowerAssist": false, "firstTowerKill": true, "gameEndedInEarlySurrender": false, "gameEndedInSurrender": true, "getBackPings": 0, "goldEarned": 7313, "goldSpent": 6625, "holdPings": 0, "individualPosition": "TOP", "inhibitorKills": 0, "inhibitorTakedowns": 0, "inhibitorsLost": 0, "item0": 2021, "item1": 1037, "item2": 0, "item3": 3047, "item4": 6692, "item5": 1055, "item6": 3364, "itemsPurchased": 10, "killingSprees": 1, "kills": 3, "lane": "NONE", "largestCriticalStrike": 0, "largestKillingSpree": 3, "largestMultiKill": 1, "longestTimeSpentLiving": 0, "magicDamageDealt": 4317, "magicDamageDealtToChampions": 1106, "magicDamageTaken": 1016, "missions": {"playerScore0": 0, "playerScore1": 0, "playerScore2": 0, "playerScore3": 0, "playerScore4": 0, "playerScore5": 0, "playerScore6": 0, "playerScore7": 0, "playerScore8": 0, "playerScore9": 0, "playerScore10": 0, "playerScore11": 0}, "needVisionPings": 0, "neutralMinionsKilled": 0, "nexusKills": 0, "nexusLost": 0, "nexusTakedowns": 0, "objectivesStolen": 0, "objectivesStolenAssists": 0, "onMyWayPings": 0, "participantId": 6, "pentaKills": 0, "perks": {"statPerks": {"defense": 5011, "flex": 5008, "offense": 5008}, "styles": [{"description": "primaryStyle", "selections": [{"perk": 8010, "var1": 323, "var2": 0, "var3": 0}, {"perk": 9101, "var1": 718, "var2": 0, "var3": 0}, {"perk": 9104, "var1": 0, "var2": 0, "var3": 0}, {"perk": 8017, "var1": 475, "var2": 0, "var3": 0}], "style": 8000}, {"description": "subStyle", "selections": [{"perk": 8444, "var1": 752, "var2": 0, "var3": 0}, {"perk": 8242, "var1": 48, "var2": 0, "var3": 0}], "style": 8400}]}, "physicalDamageDealt": 72595, "physicalDamageDealtToChampions": 11699, "physicalDamageTaken": 10380, "placement": 0, "playerAugment1": 0, "playerAugment2": 0, "playerAugment3": 0, "playerAugment4": 0, "playerAugment5": 0, "playerAugment6": 0, "playerSubteamId": 0, "profileIcon": 6502, "pushPings": 0, "puuid": "XLNZ3OrbT5DcPp-IL98dkC_uT1fF8ihkGaZ0f9yUsQcFnV0UPzqtWef77c3MTRzQP7f3_LH_oLN0pw", "quadraKills": 0, "retreatPings": 0, "riotIdGameName": "Robo", "riotIdTagline": "ROBS", "role": "SUPPORT", "roleBoundItem": 1220, "sightWardsBoughtInGame": 0, "spell1Casts": 49, "spell2Casts": 19, "spell3Casts": 49, "spell4Casts": 2, "subteamPlacement": 0, "summoner1Casts": 1, "summoner1Id": 14, "summoner2Casts": 1, "summoner2Id": 4, "summonerId": "ZvT7VYJAU_Q5yIyV0lpNP8E6ixEaco6wlRfJRfgFJJu0", "summonerLevel": 722, "summonerName": "", "teamEarlySurrendered": false, "teamId": 200, "teamPosition": "TOP", "timeCCingOthers": 19, "timePlayed": 921, "totalAllyJungleMinionsKilled": 0, "totalDamageDealt": 78798, "totalDamageDealtToChampions": 12916, "totalDamageShieldedOnTeammates": 0, "totalDamageTaken": 11397, "totalEnemyJungleMinionsKilled": 0, "totalHeal": 5819, "totalHealsOnTeammates": 0, "totalMinionsKilled": 159, "totalTimeCCDealt": 20, "totalTimeSpentDead": 0, "totalUnitsHealed": 1, "tripleKills": 0, "trueDamageDealt": 1885, "trueDamageDealtToChampions": 110, "trueDamageTaken": 0, "turretKills": 1, "turretTakedowns": 1, "turretsLost": 0, "unrealKills": 0, "visionClearedPings": 0, "visionScore": 13, "visionWardsBoughtInGame": 0, "wardsKilled": 1, "wardsPlaced": 5, "win": true}, {"PlayerBehavior": {"PlayerBehavior_IsHeroInCombat": 0}, "PlayerScore0": 0, "PlayerScore1": 0, "PlayerScore10": 0, "PlayerScore11": 0, "PlayerScore2": 0, "PlayerScore3": 0, "PlayerScore4": 0, "PlayerScore5": 0, "PlayerScore6": 0, "PlayerScore7": 0, "PlayerScore8": 0, "PlayerScore9": 0, "allInPings": 0, "assistMePings": 0, "assists": 3, "baronKills": 0, "basicPings": 0, "challenges": {"12AssistStreakCount": 0, "HealFromMapSources": 0, "InfernalScalePickup": 0, "SWARM_DefeatAatrox": 0, "SWARM_DefeatBriar": 0, "SWARM_DefeatMiniBosses": 0, "SWARM_EvolveWeapon": 0, "SWARM_Have3Passives": 0, "SWARM_KillEnemy": 0, "SWARM_PickupGold": 0, "SWARM_ReachLevel50": 0, "SWARM_Survive15Min": 0, "SWARM_WinWith5EvolvedWeapons": 0, "abilityUses": 216, "acesBefore15Minutes": 0, "alliedJungleMonsterKills": 66, "baronTakedowns": 0, "blastConeOppositeOpponentCount": 0, "bountyGold": 177.23330688476562, "buffsStolen": 0, "completeSupportQuestInTime": 0, "controlWardsPlaced": 0, "damagePerMinute": 236.1631009757452, "damageTakenOnTeamPercentage": 0.27139937529090197, "dancedWithRiftHerald": 0, "deathsByEnemyChamps": 0, "dodgeSkillShotsSmallWindow": 0, "doubleAces": 0, "dragonTakedowns": 1, "earliestDragonTakedown": 532.9533764160001, "earlyLaningPhaseGoldExpAdvantage": 0, "effectiveHealAndShielding": 0, "elderDragonKillsWithOpposingSoul": 0, "elderDragonMultikills": 0, "enemyChampionImmobilizations": 2, "enemyJungleMonsterKills": 9, "epicMonsterKillsNearEnemyJungler": 0, "epicMonsterKillsWithin30SecondsOfSpawn": 0, "epicMonsterSteals": 0, "epicMonsterStolenWithoutSmite": 0, "firstTurretKilled": 1, "firstTurretKilledTime": 806.4253690620001, "fistBumpParticipation": 0, "flawlessAces": 0, "fullTeamTakedown": 0, "gameLength": 921.399431054, "goldPerMinute": 542.9032886180318, "hadOpenNexus": 0, "immobilizeAndKillWithAlly": 2, "initialBuffCount": 2, "initialCrabCount": 2, "jungleCsBefore10Minutes": 84.00000011920929, "junglerKillsEarlyJungle": 0, "junglerTakedownsNearDamagedEpicMonster": 1, "kTurretsDestroyedBeforePlatesFall": 0, "kda": 10, "killAfterHiddenWithAlly": 0, "killParticipation": 0.5882352941176471, "killedChampTookFullTeamDamageSurvived": 0, "killingSprees": 1, "killsNearEnemyTurret": 1, "killsOnLanersEarlyJungleAsJungler": 1, "killsOnRecentlyHealedByAramPack": 0, "killsUnderOwnTurret": 1, "killsWithHelpFromEpicMonster": 1, "knockEnemyIntoTeamAndKill": 0, "landSkillShotsEarlyGame": 1, "laneMinionsFirst10Minutes": 2, "laningPhaseGoldExpAdvantage": 1, "legendaryCount": 0, "legendaryItemUsed": [3179, 6698], "lostAnInhibitor": 0, "maxCsAdvantageOnLaneOpponent": 39.00000008940697, "maxKillDeficit": 3, "maxLevelLeadLaneOpponent": 2, "mejaisFullStackInTime": 0, "moreEnemyJungleThanOpponent": -59.50000008940697, "multiKillOneSpell": 0, "multiTurretRiftHeraldCount": 0, "multikills": 1, "multikillsAfterAggressiveFlash": 0, "outerTurretExecutesBefore10Minutes": 0, "outnumberedKills": 1, "outnumberedNexusKill": 0, "perfectDragonSoulsTaken": 0, "perfectGame": 0, "pickKillWithAlly": 5, "playedChampSelectPosition": 1, "poroExplosions": 0, "quickCleanse": 0, "quickFirstTurret": 0, "quickSoloKills": 0, "riftHeraldTakedowns": 0, "saveAllyFromDeath": 0, "scuttleCrabKills": 3, "skillshotsDodged": 0, "skillshotsHit": 8, "snowballsHit": 0, "soloBaronKills": 0, "soloKills": 1, "stealthWardsPlaced": 2, "survivedSingleDigitHpCount": 0, "survivedThreeImmobilizesInFight": 3, "takedownOnFirstTurret": 0, "takedowns": 10, "takedownsAfterGainingLevelAdvantage": 0, "takedownsBeforeJungleMinionSpawn": 0, "takedownsFirstXMinutes": 8, "takedownsInAlcove": 0, "takedownsInEnemyFountain": 0, "teamBaronKills": 0, "teamDamagePercentage": 0.0774484155202102, "teamElderDragonKills": 0, "teamRiftHeraldKills": 0, "tookLargeDamageSurvived": 0, "turretPlatesTaken": 1, "turretTakedowns": 0, "turretsTakenWithRiftHerald": 0, "twentyMinionsIn3SecondsCount": 0, "twoWardsOneSweeperCount": 0, "unseenRecalls": 0, "visionScoreAdvantageLaneOpponent": 0.3765004873275757, "visionScorePerMinute": 1.0206889184258525, "voidMonsterKill": 0, "wardTakedowns": 4, "wardTakedownsBefore20M": 4, "wardsGuarded": 0}, "champExperience": 8420, "champLevel": 11, "championId": 107, "championName": "Rengar", "championTransform": 0, "commandPings": 4, "consumablesPurchased": 0, "damageDealtToBuildings": 0, "damageDealtToEpicMonsters": 5201, "damageDealtToObjectives": 5201, "damageDealtToTurrets": 0, "damageSelfMitigated": 5871, "dangerPings": 0, "deaths": 0, "detectorWardsPlaced": 0, "doubleKills": 1, "dragonKills": 1, "eligibleForProgression": true, "enemyMissingPings": 1, "enemyVisionPings": 1, "firstBloodAssist": false, "firstBloodKill": false, "firstTowerAssist": false, "firstTowerKill": false, "gameEndedInEarlySurrender": false, "gameEndedInSurrender": true, "getBackPings": 3, "goldEarned": 8337, "goldSpent": 7400, "holdPings": 0, "individualPosition": "JUNGLE", "inhibitorKills": 0, "inhibitorTakedowns": 0, "inhibitorsLost": 0, "item0": 3134, "item1": 6698, "item2": 3179, "item3": 1001, "item4": 0, "item5": 0, "item6": 3364, "itemsPurchased": 13, "killingSprees": 1, "kills": 7, "lane": "NONE", "largestCriticalStrike": 0, "largestKillingSpree": 7, "largestMultiKill": 2, "longestTimeSpentLiving": 0, "magicDamageDealt": 16339, "magicDamageDealtToChampions": 476, "magicDamageTaken": 3947, "missions": {"playerScore0": 0, "playerScore1": 0, "playerScore2": 0, "playerScore3": 0, "playerScore4": 0, "playerScore5": 0, "playerScore6": 0, "playerScore7": 0, "playerScore8": 0, "playerScore9": 0, "playerScore10": 0, "playerScore11": 0}, "needVisionPings": 1, "neutralMinionsKilled": 128, "nexusKills": 0, "nexusLost": 0, "nexusTakedowns": 0, "objectivesStolen": 0, "objectivesStolenAssists": 0, "onMyWayPings": 22, "participantId": 7, "pentaKills": 0, "perks": {"statPerks": {"defense": 5001, "flex": 5008, "offense": 5005}, "styles": [{"description": "primaryStyle", "selections": [{"perk": 8010, "var1": 5, "var2": 0, "var3": 0}, {"perk": 9111, "var1": 634, "var2": 200, "var3": 0}, {"perk": 9104, "var1": 9, "var2": 40, "var3": 0}, {"perk": 8014, "var1": 189, "var2": 0, "var3": 0}], "style": 8000}, {"description": "subStyle", "selections": [{"perk": 8143, "var1": 289, "var2": 0, "var3": 0}, {"perk": 8105, "var1": 32, "var2": 4, "var3": 0}], "style": 8100}]}, "physicalDamageDealt": 72659, "physicalDamageDealtToChampions": 2847, "physicalDamageTaken": 7924, "placement": 0, "playerAugment1": 0, "playerAugment2": 0, "playerAugment3": 0, "playerAugment4": 0, "playerAugment5": 0, "playerAugment6": 0, "playerSubteamId": 0, "profileIcon": 657, "pushPings": 0, "puuid": "Dc1BTdABq49Dnd4NS5ZSFWwnauzzLyXRTyPdyPbDkhuuPGSPAykkPVHnib-eF0UviZn9DeoLN2VBIw", "quadraKills": 0, "retreatPings": 0, "riotIdGameName": "Breper", "riotIdTagline": "Rengo", "role": "SUPPORT", "roleBoundItem": 1209, "sightWardsBoughtInGame": 0, "spell1Casts": 116, "spell2Casts": 46, "spell3Casts": 50, "spell4Casts": 4, "subteamPlacement": 0, "summoner1Casts": 2, "summoner1Id": 4, "summoner2Casts": 6, "summoner2Id": 11, "summonerId": "Ar3vkY0KqlGnpEurGc9ws1jCCBIJx6p6t9iCBHazLc_c-w", "summonerLevel": 767, "summonerName": "", "teamEarlySurrendered": false, "teamId": 200, "teamPosition": "JUNGLE", "timeCCingOthers": 5, "timePlayed": 921, "totalAllyJungleMinionsKilled": 96, "totalDamageDealt": 138099, "totalDamageDealtToChampions": 3626, "totalDamageShieldedOnTeammates": 0, "totalDamageTaken": 12133, "totalEnemyJungleMinionsKilled": 8, "totalHeal": 8376, "totalHealsOnTeammates": 0, "totalMinionsKilled": 11, "totalTimeCCDealt": 272, "totalTimeSpentDead": 0, "totalUnitsHealed": 1, "tripleKills": 0, "trueDamageDealt": 49100, "trueDamageDealtToChampions": 302, "trueDamageTaken": 261, "turretKills": 0, "turretTakedowns": 0, "turretsLost": 0, "unrealKills": 0, "visionClearedPings": 0, "visionScore": 15, "visionWardsBoughtInGame": 0, "wardsKilled": 4, "wardsPlaced": 2, "win": true}, {"PlayerBehavior": {"PlayerBehavior_IsHeroInCombat": 0}, "PlayerScore0": 0, "PlayerScore1": 0, "PlayerScore10": 0, "PlayerScore11": 0, "PlayerScore2": 0, "PlayerScore3": 0, "PlayerScore4": 0, "PlayerScore5": 0, "PlayerScore6": 0, "PlayerScore7": 0, "PlayerScore8": 0, "PlayerScore9": 0, "allInPings": 0, "assistMePings": 0, "assists": 6, "baronKills": 0, "basicPings": 0, "challenges": {"12AssistStreakCount": 0, "HealFromMapSources": 176, "InfernalScalePickup": 0, "SWARM_DefeatAatrox": 0, "SWARM_DefeatBriar": 0, "SWARM_DefeatMiniBosses": 0, "SWARM_EvolveWeapon": 0, "SWARM_Have3Passives": 0, "SWARM_KillEnemy": 0, "SWARM_PickupGold": 0, "SWARM_ReachLevel50": 0, "SWARM_Survive15Min": 0, "SWARM_WinWith5EvolvedWeapons": 0, "abilityUses": 216, "acesBefore15Minutes": 0, "alliedJungleMonsterKills": 0, "baronTakedowns": 0, "blastConeOppositeOpponentCount": 0, "bountyGold": 0, "buffsStolen": 0, "completeSupportQuestInTime": 0, "controlWardsPlaced": 0, "damagePerMinute": 1014.1316360821985, "damageTakenOnTeamPercentage": 0.17597174689364542, "dancedWithRiftHerald": 0, "deathsByEnemyChamps": 2, "dodgeSkillShotsSmallWindow": 0, "doubleAces": 0, "dragonTakedowns": 0, "earlyLaningPhaseGoldExpAdvantage": 0, "effectiveHealAndShielding": 0, "elderDragonKillsWithOpposingSoul": 0, "elderDragonMultikills": 0, "enemyChampionImmobilizations": 97, "enemyJungleMonsterKills": 0, "epicMonsterKillsNearEnemyJungler": 0, "epicMonsterKillsWithin30SecondsOfSpawn": 0, "epicMonsterSteals": 0, "epicMonsterStolenWithoutSmite": 0, "firstTurretKilled": 1, "firstTurretKilledTime": 806.4253690620001, "fistBumpParticipation": 0, "flawlessAces": 0, "fullTeamTakedown": 0, "gameLength": 921.399431054, "getTakedownsInAllLanesEarlyJungleAsLaner": 0, "goldPerMinute": 426.32248054058493, "hadOpenNexus": 0, "highestChampionDamage": 1, "highestCrowdControlScore": 1, "immobilizeAndKillWithAlly": 6, "initialBuffCount": 0, "initialCrabCount": 0, "jungleCsBefore10Minutes": 0, "junglerTakedownsNearDamagedEpicMonster": 0, "kTurretsDestroyedBeforePlatesFall": 0, "kda": 4.5, "killAfterHiddenWithAlly": 1, "killParticipation": 0.5294117647058824, "killedChampTookFullTeamDamageSurvived": 0, "killingSprees": 0, "killsNearEnemyTurret": 1, "killsOnOtherLanesEarlyJungleAsLaner": 0, "killsOnRecentlyHealedByAramPack": 0, "killsUnderOwnTurret": 0, "killsWithHelpFromEpicMonster": 0, "knockEnemyIntoTeamAndKill": 7, "landSkillShotsEarlyGame": 19, "laneMinionsFirst10Minutes": 67, "laningPhaseGoldExpAdvantage": 0, "legendaryCount": 0, "legendaryItemUsed": [6655], "lostAnInhibitor": 0, "maxCsAdvantageOnLaneOpponent": 5, "maxKillDeficit": 3, "maxLevelLeadLaneOpponent": 2, "mejaisFullStackInTime": 0, "moreEnemyJungleThanOpponent": 0, "multiKillOneSpell": 0, "multiTurretRiftHeraldCount": 0, "multikills": 0, "multikillsAfterAggressiveFlash": 0, "outerTurretExecutesBefore10Minutes": 0, "outnumberedKills": 0, "outnumberedNexusKill": 0, "perfectDragonSoulsTaken": 0, "perfectGame": 0, "pickKillWithAlly": 4, "playedChampSelectPosition": 1, "poroExplosions": 0, "quickCleanse": 0, "quickFirstTurret": 0, "quickSoloKills": 0, "riftHeraldTakedowns": 0, "saveAllyFromDeath": 0, "scuttleCrabKills": 0, "skillshotsDodged": 3, "skillshotsHit": 57, "snowballsHit": 0, "soloBaronKills": 0, "soloKills": 1, "stealthWardsPlaced": 4, "survivedSingleDigitHpCount": 0, "survivedThreeImmobilizesInFight": 4, "takedownOnFirstTurret": 0, "takedowns": 9, "takedownsAfterGainingLevelAdvantage": 0, "takedownsBeforeJungleMinionSpawn": 0, "takedownsFirstXMinutes": 7, "takedownsInAlcove": 0, "takedownsInEnemyFountain": 0, "teamBaronKills": 0, "teamDamagePercentage": 0.3325790016263013, "teamElderDragonKills": 0, "teamRiftHeraldKills": 0, "tookLargeDamageSurvived": 0, "turretPlatesTaken": 3, "turretTakedowns": 0, "turretsTakenWithRiftHerald": 0, "twentyMinionsIn3SecondsCount": 0, "twoWardsOneSweeperCount": 0, "unseenRecalls": 0, "visionScoreAdvantageLaneOpponent": 0.8543741703033447, "visionScorePerMinute": 0.5268636321337847, "voidMonsterKill": 0, "wardTakedowns": 0, "wardTakedownsBefore20M": 0, "wardsGuarded": 0}, "champExperience": 8478, "champLevel": 11, "championId": 134, "championName": "Syndra", "championTransform": 0, "commandPings": 8, "consumablesPurchased": 2, "damageDealtToBuildings": 3549, "damageDealtToEpicMonsters": 0, "damageDealtToObjectives": 3549, "damageDealtToTurrets": 3549, "damageSelfMitigated": 3040, "dangerPings": 0, "deaths": 2, "detectorWardsPlaced": 0, "doubleKills": 0, "dragonKills": 0, "eligibleForProgression": true, "enemyMissingPings": 10, "enemyVisionPings": 0, "firstBloodAssist": false, "firstBloodKill": false, "firstTowerAssist": false, "firstTowerKill": false, "gameEndedInEarlySurrender": false, "gameEndedInSurrender": true, "getBackPings": 0, "goldEarned": 6546, "goldSpent": 5600, "holdPings": 0, "individualPosition": "MIDDLE", "inhibitorKills": 0, "inhibitorTakedowns": 0, "inhibitorsLost": 0, "item0": 1056, "item1": 1082, "item2": 6655, "item3": 3171, "item4": 3145, "item5": 0, "item6": 3363, "itemsPurchased": 14, "killingSprees": 1, "kills": 3, "lane": "NONE", "largestCriticalStrike": 0, "largestKillingSpree": 2, "largestMultiKill": 1, "longestTimeSpentLiving": 530, "magicDamageDealt": 57763, "magicDamageDealtToChampions": 13314, "magicDamageTaken": 1207, "missions": {"playerScore0": 0, "playerScore1": 0, "playerScore2": 0, "playerScore3": 0, "playerScore4": 0, "playerScore5": 0, "playerScore6": 0, "playerScore7": 0, "playerScore8": 0, "playerScore9": 0, "playerScore10": 0, "playerScore11": 0}, "needVisionPings": 0, "neutralMinionsKilled": 0, "nexusKills": 0, "nexusLost": 0, "nexusTakedowns": 0, "objectivesStolen": 0, "objectivesStolenAssists": 0, "onMyWayPings": 13, "participantId": 8, "pentaKills": 0, "perks": {"statPerks": {"defense": 5011, "flex": 5008, "offense": 5005}, "styles": [{"description": "primaryStyle", "selections": [{"perk": 8369, "var1": 475, "var2": 386, "var3": 0}, {"perk": 8321, "var1": 206, "var2": 0, "var3": 0}, {"perk": 8313, "var1": 3, "var2": 0, "var3": 0}, {"perk": 8316, "var1": 5, "var2": 10, "var3": 0}], "style": 8300}, {"description": "subStyle", "selections": [{"perk": 8226, "var1": 250, "var2": 321, "var3": 0}, {"perk": 8210, "var1": 4, "var2": 0, "var3": 0}], "style": 8200}]}, "physicalDamageDealt": 6599, "physicalDamageDealtToChampions": 1408, "physicalDamageTaken": 5781, "placement": 0, "playerAugment1": 0, "playerAugment2": 0, "playerAugment3": 0, "playerAugment4": 0, "playerAugment5": 0, "playerAugment6": 0, "playerSubteamId": 0, "profileIcon": 7015, "pushPings": 0, "puuid": "Pr48DetWYymD2yHSbCibB5rTHlBhLdCMORXDyLm521PAGIU2AZ8d9TqZmqi3T6QmIq1-u5kV0fDRSw", "quadraKills": 0, "retreatPings": 0, "riotIdGameName": "papoi", "riotIdTagline": "minio", "role": "SUPPORT", "roleBoundItem": 1206, "sightWardsBoughtInGame": 0, "spell1Casts": 87, "spell2Casts": 91, "spell3Casts": 33, "spell4Casts": 5, "subteamPlacement": 0, "summoner1Casts": 3, "summoner1Id": 4, "summoner2Casts": 3, "summoner2Id": 6, "summonerId": "Xfdp2W0qIAueiy1xjRZ7zVB6ZNNCxidP45FOJAjePbpazEs", "summonerLevel": 100, "summonerName": "", "teamEarlySurrendered": false, "teamId": 200, "teamPosition": "MIDDLE", "timeCCingOthers": 39, "timePlayed": 921, "totalAllyJungleMinionsKilled": 0, "totalDamageDealt": 70553, "totalDamageDealtToChampions": 15573, "totalDamageShieldedOnTeammates": 0, "totalDamageTaken": 7867, "totalEnemyJungleMinionsKilled": 0, "totalHeal": 1084, "totalHealsOnTeammates": 0, "totalMinionsKilled": 109, "totalTimeCCDealt": 301, "totalTimeSpentDead": 49, "totalUnitsHealed": 1, "tripleKills": 0, "trueDamageDealt": 6190, "trueDamageDealtToChampions": 850, "trueDamageTaken": 878, "turretKills": 0, "turretTakedowns": 0, "turretsLost": 0, "unrealKills": 0, "visionClearedPings": 0, "visionScore": 8, "visionWardsBoughtInGame": 0, "wardsKilled": 0, "wardsPlaced": 4, "win": true}, {"PlayerBehavior": {"PlayerBehavior_IsHeroInCombat": 0}, "PlayerScore0": 0, "PlayerScore1": 0, "PlayerScore10": 0, "PlayerScore11": 0, "PlayerScore2": 0, "PlayerScore3": 0, "PlayerScore4": 0, "PlayerScore5": 0, "PlayerScore6": 0, "PlayerScore7": 0, "PlayerScore8": 0, "PlayerScore9": 0, "allInPings": 0, "assistMePings": 1, "assists": 5, "baronKills": 0, "basicPings": 0, "challenges": {"12AssistStreakCount": 0, "HealFromMapSources": 0, "InfernalScalePickup": 0, "SWARM_DefeatAatrox": 0, "SWARM_DefeatBriar": 0, "SWARM_DefeatMiniBosses": 0, "SWARM_EvolveWeapon": 0, "SWARM_Have3Passives": 0, "SWARM_KillEnemy": 0, "SWARM_PickupGold": 0, "SWARM_ReachLevel50": 0, "SWARM_Survive15Min": 0, "SWARM_WinWith5EvolvedWeapons": 0, "abilityUses": 186, "acesBefore15Minutes": 0, "alliedJungleMonsterKills": 0, "baronTakedowns": 0, "blastConeOppositeOpponentCount": 0, "bountyGold": 0, "buffsStolen": 0, "completeSupportQuestInTime": 0, "controlWardsPlaced": 0, "damagePerMinute": 616.0265404732863, "damageTakenOnTeamPercentage": 0.14154992434692262, "dancedWithRiftHerald": 0, "deathsByEnemyChamps": 1, "dodgeSkillShotsSmallWindow": 0, "doubleAces": 0, "dragonTakedowns": 1, "earliestDragonTakedown": 532.9533764160001, "earlyLaningPhaseGoldExpAdvantage": 1, "effectiveHealAndShielding": 0, "elderDragonKillsWithOpposingSoul": 0, "elderDragonMultikills": 0, "enemyChampionImmobilizations": 0, "enemyJungleMonsterKills": 0, "epicMonsterKillsNearEnemyJungler": 0, "epicMonsterKillsWithin30SecondsOfSpawn": 0, "epicMonsterSteals": 0, "epicMonsterStolenWithoutSmite": 0, "firstTurretKilled": 1, "firstTurretKilledTime": 806.4253690620001, "fistBumpParticipation": 0, "flawlessAces": 0, "fullTeamTakedown": 0, "gameLength": 921.399431054, "getTakedownsInAllLanesEarlyJungleAsLaner": 0, "goldPerMinute": 498.8492700369511, "hadOpenNexus": 0, "immobilizeAndKillWithAlly": 0, "initialBuffCount": 0, "initialCrabCount": 0, "jungleCsBefore10Minutes": 0, "junglerTakedownsNearDamagedEpicMonster": 0, "kTurretsDestroyedBeforePlatesFall": 1, "kda": 8, "killAfterHiddenWithAlly": 0, "killParticipation": 0.47058823529411764, "killedChampTookFullTeamDamageSurvived": 0, "killingSprees": 0, "killsNearEnemyTurret": 1, "killsOnOtherLanesEarlyJungleAsLaner": 0, "killsOnRecentlyHealedByAramPack": 0, "killsUnderOwnTurret": 0, "killsWithHelpFromEpicMonster": 0, "knockEnemyIntoTeamAndKill": 0, "landSkillShotsEarlyGame": 24, "laneMinionsFirst10Minutes": 82, "laningPhaseGoldExpAdvantage": 0, "legendaryCount": 0, "legendaryItemUsed": [3078, 3004], "lostAnInhibitor": 0, "maxCsAdvantageOnLaneOpponent": 50, "maxKillDeficit": 3, "maxLevelLeadLaneOpponent": 2, "mejaisFullStackInTime": 0, "moreEnemyJungleThanOpponent": 0, "multiKillOneSpell": 0, "multiTurretRiftHeraldCount": 0, "multikills": 0, "multikillsAfterAggressiveFlash": 0, "outerTurretExecutesBefore10Minutes": 0, "outnumberedKills": 1, "outnumberedNexusKill": 0, "perfectDragonSoulsTaken": 0, "perfectGame": 0, "pickKillWithAlly": 6, "playedChampSelectPosition": 1, "poroExplosions": 0, "quickCleanse": 0, "quickFirstTurret": 0, "quickSoloKills": 0, "riftHeraldTakedowns": 0, "saveAllyFromDeath": 0, "scuttleCrabKills": 0, "skillshotsDodged": 10, "skillshotsHit": 46, "snowballsHit": 0, "soloBaronKills": 0, "soloKills": 0, "stealthWardsPlaced": 5, "survivedSingleDigitHpCount": 0, "survivedThreeImmobilizesInFight": 0, "takedownOnFirstTurret": 0, "takedowns": 8, "takedownsAfterGainingLevelAdvantage": 0, "takedownsBeforeJungleMinionSpawn": 0, "takedownsFirstXMinutes": 6, "takedownsInAlcove": 0, "takedownsInEnemyFountain": 0, "teamBaronKills": 0, "teamDamagePercentage": 0.20202258219395877, "teamElderDragonKills": 0, "teamRiftHeraldKills": 0, "tookLargeDamageSurvived": 0, "turretPlatesTaken": 8, "turretTakedowns": 2, "turretsTakenWithRiftHerald": 0, "twentyMinionsIn3SecondsCount": 0, "twoWardsOneSweeperCount": 0, "unseenRecalls": 0, "visionScoreAdvantageLaneOpponent": -0.5580084323883057, "visionScorePerMinute": 0.5177413290388319, "voidMonsterKill": 0, "wardTakedowns": 1, "wardTakedownsBefore20M": 1, "wardsGuarded": 0}, "champExperience": 6580, "champLevel": 10, "championId": 81, "championName": "Ezreal", "championTransform": 0, "commandPings": 2, "consumablesPurchased": 1, "damageDealtToBuildings": 7651, "damageDealtToEpicMonsters": 1573, "damageDealtToObjectives": 9224, "damageDealtToTurrets": 7651, "damageSelfMitigated": 3078, "dangerPings": 0, "deaths": 1, "detectorWardsPlaced": 0, "doubleKills": 0, "dragonKills": 0, "eligibleForProgression": true, "enemyMissingPings": 4, "enemyVisionPings": 3, "firstBloodAssist": false, "firstBloodKill": false, "firstTowerAssist": false, "firstTowerKill": false, "gameEndedInEarlySurrender": false, "gameEndedInSurrender": true, "getBackPings": 0, "goldEarned": 7660, "goldSpent": 6883, "holdPings": 0, "individualPosition": "BOTTOM", "inhibitorKills": 0, "inhibitorTakedowns": 0, "inhibitorsLost": 0, "item0": 1055, "item1": 3004, "item2": 0, "item3": 3078, "item4": 0, "item5": 0, "item6": 3363, "itemsPurchased": 15, "killingSprees": 1, "kills": 3, "lane": "NONE", "largestCriticalStrike": 0, "largestKillingSpree": 2, "largestMultiKill": 1, "longestTimeSpentLiving": 196, "magicDamageDealt": 5426, "magicDamageDealtToChampions": 2343, "magicDamageTaken": 881, "missions": {"playerScore0": 0, "playerScore1": 0, "playerScore2": 0, "playerScore3": 0, "playerScore4": 0, "playerScore5": 0, "playerScore6": 0, "playerScore7": 0, "playerScore8": 0, "playerScore9": 0, "playerScore10": 0, "playerScore11": 0}, "needVisionPings": 1, "neutralMinionsKilled": 0, "nexusKills": 0, "nexusLost": 0, "nexusTakedowns": 0, "objectivesStolen": 0, "objectivesStolenAssists": 0, "onMyWayPings": 14, "participantId": 9, "pentaKills": 0, "perks": {"statPerks": {"defense": 5011, "flex": 5008, "offense": 5005}, "styles": [{"description": "primaryStyle", "selections": [{"perk": 8008, "var1": 122, "var2": 122, "var3": 0}, {"perk": 8009, "var1": 1548, "var2": 0, "var3": 0}, {"perk": 9103, "var1": 0, "var2": 0, "var3": 0}, {"perk": 8017, "var1": 488, "var2": 0, "var3": 0}], "style": 8000}, {"description": "subStyle", "selections": [{"perk": 8304, "var1": 7, "var2": 3, "var3": 0}, {"perk": 8316, "var1": 7, "var2": 10, "var3": 0}], "style": 8300}]}, "physicalDamageDealt": 66475, "physicalDamageDealtToChampions": 7116, "physicalDamageTaken": 5441, "placement": 0, "playerAugment1": 0, "playerAugment2": 0, "playerAugment3": 0, "playerAugment4": 0, "playerAugment5": 0, "playerAugment6": 0, "playerSubteamId": 0, "profileIcon": 4568, "pushPings": 0, "puuid": "vcwAvwlpCKr-UXe349t9Ksw1oJw7m1kQQBev4yCBZfRYi4qYV5KZSvJmBh3L_T5KOcslUfrceaI-kw", "quadraKills": 0, "retreatPings": 0, "riotIdGameName": "Pl Torvic", "riotIdTagline": "Drica", "role": "SUPPORT", "roleBoundItem": 2422, "sightWardsBoughtInGame": 0, "spell1Casts": 131, "spell2Casts": 34, "spell3Casts": 15, "spell4Casts": 6, "subteamPlacement": 0, "summoner1Casts": 3, "summoner1Id": 21, "summoner2Casts": 2, "summoner2Id": 4, "summonerId": "GcKCsu3q2FR5-XxtvujfO-Fy7A8wrPEH08zjY0FiUVFWsws", "summonerLevel": 149, "summonerName": "", "teamEarlySurrendered": false, "teamId": 200, "teamPosition": "BOTTOM", "timeCCingOthers": 0, "timePlayed": 921, "totalAllyJungleMinionsKilled": 0, "totalDamageDealt": 74117, "totalDamageDealtToChampions": 9460, "totalDamageShieldedOnTeammates": 0, "totalDamageTaken": 6328, "totalEnemyJungleMinionsKilled": 0, "totalHeal": 2107, "totalHealsOnTeammates": 0, "totalMinionsKilled": 160, "totalTimeCCDealt": 0, "totalTimeSpentDead": 12, "totalUnitsHealed": 1, "tripleKills": 0, "trueDamageDealt": 2214, "trueDamageDealtToChampions": 0, "trueDamageTaken": 5, "turretKills": 2, "turretTakedowns": 2, "turretsLost": 0, "unrealKills": 0, "visionClearedPings": 0, "visionScore": 7, "visionWardsBoughtInGame": 0, "wardsKilled": 1, "wardsPlaced": 5, "win": true}, {"PlayerBehavior": {"PlayerBehavior_IsHeroInCombat": 0}, "PlayerScore0": 0, "PlayerScore1": 0, "PlayerScore10": 0, "PlayerScore11": 0, "PlayerScore2": 0, "PlayerScore3": 0, "PlayerScore4": 0, "PlayerScore5": 0, "PlayerScore6": 0, "PlayerScore7": 0, "PlayerScore8": 0, "PlayerScore9": 0, "allInPings": 0, "assistMePings": 0, "assists": 10, "baronKills": 0, "basicPings": 0, "challenges": {"12AssistStreakCount": 0, "HealFromMapSources": 0, "InfernalScalePickup": 0, "SWARM_DefeatAatrox": 0, "SWARM_DefeatBriar": 0, "SWARM_DefeatMiniBosses": 0, "SWARM_EvolveWeapon": 0, "SWARM_Have3Passives": 0, "SWARM_KillEnemy": 0, "SWARM_PickupGold": 0, "SWARM_ReachLevel50": 0, "SWARM_Survive15Min": 0, "SWARM_WinWith5EvolvedWeapons": 0, "abilityUses": 97, "acesBefore15Minutes": 0, "alliedJungleMonsterKills": 0, "baronTakedowns": 0, "blastConeOppositeOpponentCount": 0, "bountyGold": 0, "buffsStolen": 0, "completeSupportQuestInTime": 1, "controlWardsPlaced": 0, "damagePerMinute": 341.86908293973545, "damageTakenOnTeamPercentage": 0.15614415963223088, "dancedWithRiftHerald": 0, "deathsByEnemyChamps": 3, "dodgeSkillShotsSmallWindow": 0, "doubleAces": 0, "dragonTakedowns": 1, "earliestDragonTakedown": 532.9533764160001, "earlyLaningPhaseGoldExpAdvantage": 0, "effectiveHealAndShielding": 3815.888916015625, "elderDragonKillsWithOpposingSoul": 0, "elderDragonMultikills": 0, "enemyChampionImmobilizations": 3, "enemyJungleMonsterKills": 0, "epicMonsterKillsNearEnemyJungler": 0, "epicMonsterKillsWithin30SecondsOfSpawn": 0, "epicMonsterSteals": 0, "epicMonsterStolenWithoutSmite": 0, "fasterSupportQuestCompletion": 1, "firstTurretKilled": 1, "firstTurretKilledTime": 806.4253690620001, "fistBumpParticipation": 0, "flawlessAces": 0, "fullTeamTakedown": 0, "gameLength": 921.399431054, "getTakedownsInAllLanesEarlyJungleAsLaner": 0, "goldPerMinute": 329.65157264848995, "hadOpenNexus": 0, "highestWardKills": 1, "immobilizeAndKillWithAlly": 3, "initialBuffCount": 0, "initialCrabCount": 0, "jungleCsBefore10Minutes": 0, "junglerTakedownsNearDamagedEpicMonster": 0, "kTurretsDestroyedBeforePlatesFall": 1, "kda": 3.6666666666666665, "killAfterHiddenWithAlly": 1, "killParticipation": 0.6470588235294118, "killedChampTookFullTeamDamageSurvived": 0, "killingSprees": 0, "killsNearEnemyTurret": 0, "killsOnOtherLanesEarlyJungleAsLaner": 0, "killsOnRecentlyHealedByAramPack": 0, "killsUnderOwnTurret": 1, "killsWithHelpFromEpicMonster": 0, "knockEnemyIntoTeamAndKill": 0, "landSkillShotsEarlyGame": 0, "laneMinionsFirst10Minutes": 16, "laningPhaseGoldExpAdvantage": 1, "legendaryCount": 0, "legendaryItemUsed": [6620, 3877], "lostAnInhibitor": 0, "maxCsAdvantageOnLaneOpponent": 11, "maxKillDeficit": 3, "maxLevelLeadLaneOpponent": 2, "mejaisFullStackInTime": 0, "moreEnemyJungleThanOpponent": 0, "multiKillOneSpell": 0, "multiTurretRiftHeraldCount": 0, "multikills": 0, "multikillsAfterAggressiveFlash": 0, "outerTurretExecutesBefore10Minutes": 0, "outnumberedKills": 1, "outnumberedNexusKill": 0, "perfectDragonSoulsTaken": 0, "perfectGame": 0, "pickKillWithAlly": 7, "playedChampSelectPosition": 1, "poroExplosions": 0, "quickCleanse": 0, "quickFirstTurret": 0, "quickSoloKills": 0, "riftHeraldTakedowns": 0, "saveAllyFromDeath": 0, "scuttleCrabKills": 0, "skillshotsDodged": 11, "skillshotsHit": 3, "snowballsHit": 0, "soloBaronKills": 0, "soloKills": 0, "stealthWardsPlaced": 15, "survivedSingleDigitHpCount": 0, "survivedThreeImmobilizesInFight": 0, "takedownOnFirstTurret": 1, "takedowns": 11, "takedownsAfterGainingLevelAdvantage": 0, "takedownsBeforeJungleMinionSpawn": 0, "takedownsFirstXMinutes": 9, "takedownsInAlcove": 0, "takedownsInEnemyFountain": 0, "teamBaronKills": 0, "teamDamagePercentage": 0.11211412231476899, "teamElderDragonKills": 0, "teamRiftHeraldKills": 0, "tookLargeDamageSurvived": 0, "turretPlatesTaken": 5, "turretTakedowns": 2, "turretsTakenWithRiftHerald": 0, "twentyMinionsIn3SecondsCount": 0, "twoWardsOneSweeperCount": 0, "unseenRecalls": 0, "visionScoreAdvantageLaneOpponent": 0.5123379230499268, "visionScorePerMinute": 2.3096933916787163, "voidMonsterKill": 0, "wardTakedowns": 7, "wardTakedownsBefore20M": 7, "wardsGuarded": 0}, "champExperience": 4956, "champLevel": 8, "championId": 37, "championName": "Sona", "championTransform": 0, "commandPings": 7, "consumablesPurchased": 2, "damageDealtToBuildings": 1455, "damageDealtToEpicMonsters": 584, "damageDealtToObjectives": 2040, "damageDealtToTurrets": 1455, "damageSelfMitigated": 3170, "dangerPings": 0, "deaths": 3, "detectorWardsPlaced": 0, "doubleKills": 0, "dragonKills": 0, "eligibleForProgression": true, "enemyMissingPings": 0, "enemyVisionPings": 3, "firstBloodAssist": false, "firstBloodKill": false, "firstTowerAssist": false, "firstTowerKill": false, "gameEndedInEarlySurrender": false, "gameEndedInSurrender": true, "getBackPings": 0, "goldEarned": 5062, "goldSpent": 4400, "holdPings": 0, "individualPosition": "UTILITY", "inhibitorKills": 0, "inhibitorTakedowns": 0, "inhibitorsLost": 0, "item0": 3877, "item1": 3070, "item2": 3047, "item3": 1028, "item4": 0, "item5": 6620, "item6": 3364, "itemsPurchased": 16, "killingSprees": 0, "kills": 1, "lane": "NONE", "largestCriticalStrike": 0, "largestKillingSpree": 0, "largestMultiKill": 1, "longestTimeSpentLiving": 185, "magicDamageDealt": 9424, "magicDamageDealtToChampions": 3697, "magicDamageTaken": 2403, "missions": {"playerScore0": 0, "playerScore1": 0, "playerScore2": 0, "playerScore3": 0, "playerScore4": 0, "playerScore5": 0, "playerScore6": 0, "playerScore7": 0, "playerScore8": 0, "playerScore9": 0, "playerScore10": 0, "playerScore11": 0}, "needVisionPings": 0, "neutralMinionsKilled": 0, "nexusKills": 0, "nexusLost": 0, "nexusTakedowns": 0, "objectivesStolen": 0, "objectivesStolenAssists": 0, "onMyWayPings": 1, "participantId": 10, "pentaKills": 0, "perks": {"statPerks": {"defense": 5011, "flex": 5010, "offense": 5008}, "styles": [{"description": "primaryStyle", "selections": [{"perk": 8214, "var1": 254, "var2": 609, "var3": 0}, {"perk": 8226, "var1": 250, "var2": 215, "var3": 0}, {"perk": 8234, "var1": 5447, "var2": 0, "var3": 0}, {"perk": 8237, "var1": 214, "var2": 0, "var3": 0}], "style": 8200}, {"description": "subStyle", "selections": [{"perk": 8304, "var1": 8, "var2": 1, "var3": 5}, {"perk": 8316, "var1": 9, "var2": 10, "var3": 0}], "style": 8300}]}, "physicalDamageDealt": 4465, "physicalDamageDealtToChampions": 1552, "physicalDamageTaken": 4511, "placement": 0, "playerAugment1": 0, "playerAugment2": 0, "playerAugment3": 0, "playerAugment4": 0, "playerAugment5": 0, "playerAugment6": 0, "playerSubteamId": 0, "profileIcon": 6923, "pushPings": 0, "puuid": "h5JfrQxLv_LGxDUMrdE8z0ayb_aBM-cICTz1OXfmLRzfzhg8aezQzYuU_01rjEyHh_TrzKwubbW6nQ", "quadraKills": 0, "retreatPings": 0, "riotIdGameName": "TraczuK", "riotIdTagline": "SUPP1", "role": "SUPPORT", "roleBoundItem": 1208, "sightWardsBoughtInGame": 0, "spell1Casts": 39, "spell2Casts": 29, "spell3Casts": 27, "spell4Casts": 2, "subteamPlacement": 0, "summoner1Casts": 3, "summoner1Id": 7, "summoner2Casts": 1, "summoner2Id": 4, "summonerId": "KGSz3n5sn6ZtVAw_96ds43xkeZjh6gLsPA4tvGruD9MHcoqVng0qCPXyQw", "summonerLevel": 596, "summonerName": "", "teamEarlySurrendered": false, "teamId": 200, "teamPosition": "UTILITY", "timeCCingOthers": 5, "timePlayed": 921, "totalAllyJungleMinionsKilled": 0, "totalDamageDealt": 16608, "totalDamageDealtToChampions": 5249, "totalDamageShieldedOnTeammates": 1049, "totalDamageTaken": 6980, "totalEnemyJungleMinionsKilled": 0, "totalHeal": 4739, "totalHealsOnTeammates": 2766, "totalMinionsKilled": 27, "totalTimeCCDealt": 11, "totalTimeSpentDead": 38, "totalUnitsHealed": 4, "tripleKills": 0, "trueDamageDealt": 2718, "trueDamageDealtToChampions": 0, "trueDamageTaken": 65, "turretKills": 0, "turretTakedowns": 2, "turretsLost": 0, "unrealKills": 0, "visionClearedPings": 0, "visionScore": 35, "visionWardsBoughtInGame": 0, "wardsKilled": 7, "wardsPlaced": 15, "win": true}], "platformId": "BR1", "queueId": 420, "teams": [{"bans": [{"championId": 121, "pickTurn": 1}, {"championId": 24, "pickTurn": 2}, {"championId": -1, "pickTurn": 3}, {"championId": 36, "pickTurn": 4}, {"championId": 904, "pickTurn": 5}], "feats": {"EPIC_MONSTER_KILL": {"featState": 0}, "FIRST_BLOOD": {"featState": 0}, "FIRST_TURRET": {"featState": 0}}, "objectives": {"atakhan": {"first": false, "kills": 0}, "baron": {"first": false, "kills": 0}, "champion": {"first": true, "kills": 6}, "dragon": {"first": false, "kills": 0}, "horde": {"first": true, "kills": 3}, "inhibitor": {"first": false, "kills": 0}, "riftHerald": {"first": false, "kills": 0}, "tower": {"first": false, "kills": 0}}, "teamId": 100, "win": false}, {"bans": [{"championId": 555, "pickTurn": 6}, {"championId": 11, "pickTurn": 7}, {"championId": 36, "pickTurn": 8}, {"championId": 517, "pickTurn": 9}, {"championId": 8, "pickTurn": 10}], "feats": {"EPIC_MONSTER_KILL": {"featState": 0}, "FIRST_BLOOD": {"featState": 0}, "FIRST_TURRET": {"featState": 0}}, "objectives": {"atakhan": {"first": false, "kills": 0}, "baron": {"first": false, "kills": 0}, "champion": {"first": false, "kills": 17}, "dragon": {"first": true, "kills": 1}, "horde": {"first": false, "kills": 0}, "inhibitor": {"first": false, "kills": 0}, "riftHerald": {"first": false, "kills": 0}, "tower": {"first": true, "kills": 3}}, "teamId": 200, "win": true}], "tournamentCode": ""}}}